<?xml version="1.0" encoding="UTF-8"?>
<nex:nexml xmlns:nex="http://www.nexml.org/2009" xmlns="http://www.nexml.org/2009" xmlns:dc="http://purl.org/dc/elements/1.1/" xmlns:dcterms="http://purl.org/dc/terms/" xmlns:prism="http://prismstandard.org/namespaces/1.2/basic/" xmlns:rdf="http://www.w3.org/1999/02/22-rdf-syntax-ns#" xmlns:rdfs="http://www.w3.org/2000/01/rdf-schema#" xmlns:skos="http://www.w3.org/2004/02/skos/core#" xmlns:tb="http://purl.org/phylo/treebase/2.0/terms#" xmlns:xsd="http://www.w3.org/2001/XMLSchema#" xmlns:xsi="http://www.w3.org/2001/XMLSchema-instance" about="#S24085" generator="org.nexml.model.impl.DocumentImpl" id="S24085" version="0.9" xml:base="http://purl.org/phylo/treebase/phylows/study/TB2:">
  <meta content="Generated on Tue May 09 15:39:50 UTC 2023" datatype="xsd:string" id="meta3195419" property="skos:changeNote" xsi:type="nex:LiteralMeta"/>
  <meta content="Mapped from TreeBASE schema using org.cipres.treebase.domain.nexus.nexml.NexmlDocumentWriter@d8610d1 $Rev$" datatype="xsd:string" id="meta3195418" property="skos:historyNote" xsi:type="nex:LiteralMeta"/>
  <meta content="" datatype="xsd:string" id="meta3195417" property="prism:number" xsi:type="nex:LiteralMeta"/>
  <meta content="" datatype="xsd:string" id="meta3195416" property="prism:volume" xsi:type="nex:LiteralMeta"/>
  <meta content="Mycosphere" datatype="xsd:string" id="meta3195415" property="dc:publisher" xsi:type="nex:LiteralMeta"/>
  <meta content="Mycosphere" datatype="xsd:string" id="meta3195414" property="prism:publicationName" xsi:type="nex:LiteralMeta"/>
  <meta content="Dothideomycetes  Endophyte  Halophyte  Neocamarosporiaceae  Salt marsh" datatype="xsd:string" id="meta3195413" property="dc:subject" xsi:type="nex:LiteralMeta"/>
  <meta content="" datatype="xsd:string" id="meta3195412" property="prism:doi" xsi:type="nex:LiteralMeta"/>
  <meta content="2019" datatype="xsd:string" id="meta3195411" property="prism:publicationDate" xsi:type="nex:LiteralMeta"/>
  <meta content="Alves A." datatype="xsd:string" id="meta3195410" property="dc:contributor" xsi:type="nex:LiteralMeta"/>
  <meta content="Esteves A." datatype="xsd:string" id="meta3195409" property="dc:contributor" xsi:type="nex:LiteralMeta"/>
  <meta content="Vicente T." datatype="xsd:string" id="meta3195408" property="dc:contributor" xsi:type="nex:LiteralMeta"/>
  <meta content="Aleixo A." datatype="xsd:string" id="meta3195407" property="dc:contributor" xsi:type="nex:LiteralMeta"/>
  <meta content="Gonçalves M.F." datatype="xsd:string" id="meta3195406" property="dc:contributor" xsi:type="nex:LiteralMeta"/>
  <meta content="Gonçalves M.F., Aleixo A., Vicente T., Esteves A., &amp; Alves A." datatype="xsd:string" id="meta3195405" property="dc:creator" xsi:type="nex:LiteralMeta"/>
  <meta content="Three new species of Neocamarosporium isolated from saline environments: N. aestuarinum sp. nov., N. endophyticum sp. nov. and N. halimiones sp. nov." datatype="xsd:string" id="meta3195404" property="dc:title" xsi:type="nex:LiteralMeta"/>
  <meta content="Gonçalves M.F., Aleixo A., Vicente T., Esteves A., &amp; Alves A. 2019. Three new species of Neocamarosporium isolated from saline environments: N. aestuarinum sp. nov., N. endophyticum sp. nov. and N. halimiones sp. nov. Mycosphere, ." datatype="xsd:string" id="meta3195403" property="dcterms:bibliographicCitation" xsi:type="nex:LiteralMeta"/>
  <meta content="2019-03-04" datatype="xsd:string" id="meta3195402" property="prism:creationDate" xsi:type="nex:LiteralMeta"/>
  <meta content="2019-09-27" datatype="xsd:string" id="meta3195401" property="prism:modificationDate" xsi:type="nex:LiteralMeta"/>
  <meta content="2019-09-27" datatype="xsd:string" id="meta3195400" property="dc:date" xsi:type="nex:LiteralMeta"/>
  <meta content="Three new species of Neocamarosporium isolated from saline environments: N. aestuarinum sp. nov., N. endophyticum sp. nov. and N. halimiones sp. nov." datatype="xsd:string" id="meta3195399" property="tb:title.study" xsi:type="nex:LiteralMeta"/>
  <meta datatype="xsd:anySimpleType" id="meta3195398" property="tb:identifier.study.tb1" xsi:type="nex:LiteralMeta"/>
  <meta content="24085" datatype="xsd:string" id="meta3195397" property="tb:identifier.study" xsi:type="nex:LiteralMeta"/>
  <meta content="Study" datatype="xsd:string" id="meta3195395" property="prism:section" xsi:type="nex:LiteralMeta"/>
  <otus about="#Tls68705" id="Tls68705" label="Taxa" xml:base="http://purl.org/phylo/treebase/phylows/taxon/TB2:">
    <meta content="Mapped from TreeBASE schema using org.cipres.treebase.domain.nexus.nexml.NexmlOTUWriter@4d304fc2 $Rev$" datatype="xsd:string" id="meta3195421" property="skos:historyNote" xsi:type="nex:LiteralMeta"/>
    <otu about="#Tl3626488" id="Tl3626488" label="Foliophoma fallens CBS 284 70">
      <meta href="http://purl.org/phylo/treebase/phylows/study/TB2:S24085" id="meta3195423" rel="rdfs:isDefinedBy" xsi:type="nex:ResourceMeta"/>
    </otu>
    <otu about="#Tl3626495" id="Tl3626495" label="Foliophoma fallens CBS 161 78">
      <meta href="http://purl.org/phylo/treebase/phylows/study/TB2:S24085" id="meta3195425" rel="rdfs:isDefinedBy" xsi:type="nex:ResourceMeta"/>
    </otu>
    <otu about="#Tl3535873" id="Tl3535873" label="Pyrenochaetopsis tabarestanensis IBRC M 30051 TYPE">
      <meta href="http://purl.org/phylo/treebase/phylows/study/TB2:S24085" id="meta3195427" rel="rdfs:isDefinedBy" xsi:type="nex:ResourceMeta"/>
    </otu>
    <otu about="#Tl3535853" id="Tl3535853" label="Neocamarosporium betae CBS 109410">
      <meta href="http://purl.org/phylo/treebase/phylows/study/TB2:S24085" id="meta3195429" rel="rdfs:isDefinedBy" xsi:type="nex:ResourceMeta"/>
    </otu>
    <otu about="#Tl3535852" id="Tl3535852" label="Neocamarosporium betae CBS 112 85">
      <meta href="http://purl.org/phylo/treebase/phylows/study/TB2:S24085" id="meta3195431" rel="rdfs:isDefinedBy" xsi:type="nex:ResourceMeta"/>
    </otu>
    <otu about="#Tl3535865" id="Tl3535865" label="Neocamarosporium betae CBS 236 28">
      <meta href="http://purl.org/phylo/treebase/phylows/study/TB2:S24085" id="meta3195433" rel="rdfs:isDefinedBy" xsi:type="nex:ResourceMeta"/>
    </otu>
    <otu about="#Tl3535871" id="Tl3535871" label="Neocamarosporium betae CBS 523 66">
      <meta href="http://purl.org/phylo/treebase/phylows/study/TB2:S24085" id="meta3195435" rel="rdfs:isDefinedBy" xsi:type="nex:ResourceMeta"/>
    </otu>
    <otu about="#Tl3535870" id="Tl3535870" label="Neocamarosporium betae CBS 111 85">
      <meta href="http://purl.org/phylo/treebase/phylows/study/TB2:S24085" id="meta3195437" rel="rdfs:isDefinedBy" xsi:type="nex:ResourceMeta"/>
    </otu>
    <otu about="#Tl3626487" id="Tl3626487" label="Neocamarosporium solicola IBRC M 30257 TYPE">
      <meta href="http://purl.org/phylo/treebase/phylows/study/TB2:S24085" id="meta3195439" rel="rdfs:isDefinedBy" xsi:type="nex:ResourceMeta"/>
    </otu>
    <otu about="#Tl3535849" id="Tl3535849" label="Neocamarosporium obiones CBS 786 68">
      <meta href="http://purl.org/phylo/treebase/phylows/study/TB2:S24085" id="meta3195441" rel="rdfs:isDefinedBy" xsi:type="nex:ResourceMeta"/>
    </otu>
    <otu about="#Tl3535869" id="Tl3535869" label="Neocamarosporium obiones CBS 432 77">
      <meta href="http://purl.org/phylo/treebase/phylows/study/TB2:S24085" id="meta3195443" rel="rdfs:isDefinedBy" xsi:type="nex:ResourceMeta"/>
    </otu>
    <otu about="#Tl3535848" id="Tl3535848" label="Neocamarosporium calvescens CBS 215 57">
      <meta href="http://purl.org/phylo/treebase/phylows/study/TB2:S24085" id="meta3195445" rel="rdfs:isDefinedBy" xsi:type="nex:ResourceMeta"/>
    </otu>
    <otu about="#Tl3535874" id="Tl3535874" label="Neocamarosporium calvescens CBS 246 79">
      <meta href="http://purl.org/phylo/treebase/phylows/study/TB2:S24085" id="meta3195447" rel="rdfs:isDefinedBy" xsi:type="nex:ResourceMeta"/>
    </otu>
    <otu about="#Tl3535860" id="Tl3535860" label="Neocamarosporium calvescens CBS 343 78">
      <meta href="http://purl.org/phylo/treebase/phylows/study/TB2:S24085" id="meta3195449" rel="rdfs:isDefinedBy" xsi:type="nex:ResourceMeta"/>
    </otu>
    <otu about="#Tl3535863" id="Tl3535863" label="Neocamarosporium phragmitis MFLUCC 17 0756 TYPE">
      <meta href="http://purl.org/phylo/treebase/phylows/study/TB2:S24085" id="meta3195451" rel="rdfs:isDefinedBy" xsi:type="nex:ResourceMeta"/>
    </otu>
    <otu about="#Tl3535855" id="Tl3535855" label="Neocamarosporium korfii MFLUCC 17 0745 TYPE">
      <meta href="http://purl.org/phylo/treebase/phylows/study/TB2:S24085" id="meta3195453" rel="rdfs:isDefinedBy" xsi:type="nex:ResourceMeta"/>
    </otu>
    <otu about="#Tl3535850" id="Tl3535850" label="Neocamarosporium salsolae MFLU 17 0192 TYPE">
      <meta href="http://purl.org/phylo/treebase/phylows/study/TB2:S24085" id="meta3195455" rel="rdfs:isDefinedBy" xsi:type="nex:ResourceMeta"/>
    </otu>
    <otu about="#Tl3535875" id="Tl3535875" label="Neocamarosporium lamiacearum MFLU 15 2989 TYPE">
      <meta href="http://purl.org/phylo/treebase/phylows/study/TB2:S24085" id="meta3195457" rel="rdfs:isDefinedBy" xsi:type="nex:ResourceMeta"/>
    </otu>
    <otu about="#Tl3535859" id="Tl3535859" label="Neocamarosporium lamiacearum MFLUCC 17 0750">
      <meta href="http://purl.org/phylo/treebase/phylows/study/TB2:S24085" id="meta3195459" rel="rdfs:isDefinedBy" xsi:type="nex:ResourceMeta"/>
    </otu>
    <otu about="#Tl3626494" id="Tl3626494" label="Neocamarosporium goegapense CBS 138008 TYPE">
      <meta href="http://purl.org/phylo/treebase/phylows/study/TB2:S24085" id="meta3195461" rel="rdfs:isDefinedBy" xsi:type="nex:ResourceMeta"/>
    </otu>
    <otu about="#Tl3535877" id="Tl3535877" label="Neocamarosporium salicorniicola MFLU 15 0957 TYPE">
      <meta href="http://purl.org/phylo/treebase/phylows/study/TB2:S24085" id="meta3195463" rel="rdfs:isDefinedBy" xsi:type="nex:ResourceMeta"/>
    </otu>
    <otu about="#Tl3535846" id="Tl3535846" label="Neocamarosporium aestuarinum MUM 18 55 CMG 4 TYPE">
      <meta href="http://purl.org/phylo/treebase/phylows/study/TB2:S24085" id="meta3195465" rel="rdfs:isDefinedBy" xsi:type="nex:ResourceMeta"/>
    </otu>
    <otu about="#Tl3535876" id="Tl3535876" label="Neocamarosporium aestuarinum CAA 803">
      <meta href="http://purl.org/phylo/treebase/phylows/study/TB2:S24085" id="meta3195467" rel="rdfs:isDefinedBy" xsi:type="nex:ResourceMeta"/>
    </otu>
    <otu about="#Tl3626493" id="Tl3626493" label="Neocamarosporium jorjanensis IBRC M 30243 TYPE">
      <meta href="http://purl.org/phylo/treebase/phylows/study/TB2:S24085" id="meta3195469" rel="rdfs:isDefinedBy" xsi:type="nex:ResourceMeta"/>
    </otu>
    <otu about="#Tl3535858" id="Tl3535858" label="Neocamarosporium halimiones MUM 18 54 CAA 807 TYPE">
      <meta href="http://purl.org/phylo/treebase/phylows/study/TB2:S24085" id="meta3195471" rel="rdfs:isDefinedBy" xsi:type="nex:ResourceMeta"/>
    </otu>
    <otu about="#Tl3535851" id="Tl3535851" label="Neocamarosporium halimiones CAA 805">
      <meta href="http://purl.org/phylo/treebase/phylows/study/TB2:S24085" id="meta3195473" rel="rdfs:isDefinedBy" xsi:type="nex:ResourceMeta"/>
    </otu>
    <otu about="#Tl3535861" id="Tl3535861" label="Neocamarosporium halimiones CAA 806">
      <meta href="http://purl.org/phylo/treebase/phylows/study/TB2:S24085" id="meta3195475" rel="rdfs:isDefinedBy" xsi:type="nex:ResourceMeta"/>
    </otu>
    <otu about="#Tl3535866" id="Tl3535866" label="Neocamarosporium endophyticum CAA 809">
      <meta href="http://purl.org/phylo/treebase/phylows/study/TB2:S24085" id="meta3195477" rel="rdfs:isDefinedBy" xsi:type="nex:ResourceMeta"/>
    </otu>
    <otu about="#Tl3535872" id="Tl3535872" label="Neocamarosporium endophyticum CMG 10">
      <meta href="http://purl.org/phylo/treebase/phylows/study/TB2:S24085" id="meta3195479" rel="rdfs:isDefinedBy" xsi:type="nex:ResourceMeta"/>
    </otu>
    <otu about="#Tl3535868" id="Tl3535868" label="Neocamarosporium endophyticum MUM 18 56 CAA 808 TYPE">
      <meta href="http://purl.org/phylo/treebase/phylows/study/TB2:S24085" id="meta3195481" rel="rdfs:isDefinedBy" xsi:type="nex:ResourceMeta"/>
    </otu>
    <otu about="#Tl3535864" id="Tl3535864" label="Neocamarosporium endophyticum CAA 804">
      <meta href="http://purl.org/phylo/treebase/phylows/study/TB2:S24085" id="meta3195483" rel="rdfs:isDefinedBy" xsi:type="nex:ResourceMeta"/>
    </otu>
    <otu about="#Tl3626491" id="Tl3626491" label="Neocamarosporium chichastianum CBS 137502 TYPE">
      <meta href="http://purl.org/phylo/treebase/phylows/study/TB2:S24085" id="meta3195485" rel="rdfs:isDefinedBy" xsi:type="nex:ResourceMeta"/>
    </otu>
    <otu about="#Tl3626486" id="Tl3626486" label="Neocamarosporium persepolisi IBRC M 30134 TYPE">
      <meta href="http://purl.org/phylo/treebase/phylows/study/TB2:S24085" id="meta3195487" rel="rdfs:isDefinedBy" xsi:type="nex:ResourceMeta"/>
    </otu>
    <otu about="#Tl3535847" id="Tl3535847" label="Neocamarosporium chersinae CPC 27298 TYPE">
      <meta href="http://purl.org/phylo/treebase/phylows/study/TB2:S24085" id="meta3195489" rel="rdfs:isDefinedBy" xsi:type="nex:ResourceMeta"/>
    </otu>
    <otu about="#Tl3626492" id="Tl3626492" label="Comoclathris spartii MFLUCC 13 0214 TYPE">
      <meta href="http://purl.org/phylo/treebase/phylows/study/TB2:S24085" id="meta3195491" rel="rdfs:isDefinedBy" xsi:type="nex:ResourceMeta"/>
    </otu>
    <otu about="#Tl3626484" id="Tl3626484" label="Libertasomyces quercus CBS 134 97 TYPE">
      <meta href="http://purl.org/phylo/treebase/phylows/study/TB2:S24085" id="meta3195493" rel="rdfs:isDefinedBy" xsi:type="nex:ResourceMeta"/>
    </otu>
    <otu about="#Tl3626490" id="Tl3626490" label="Paradendryphiella salina CBS 142 60 TYPE">
      <meta href="http://purl.org/phylo/treebase/phylows/study/TB2:S24085" id="meta3195495" rel="rdfs:isDefinedBy" xsi:type="nex:ResourceMeta"/>
    </otu>
    <otu about="#Tl3626485" id="Tl3626485" label="Stemphylium vesicarium CBS 191 86 TYPE">
      <meta href="http://purl.org/phylo/treebase/phylows/study/TB2:S24085" id="meta3195497" rel="rdfs:isDefinedBy" xsi:type="nex:ResourceMeta"/>
    </otu>
    <otu about="#Tl3626489" id="Tl3626489" label="CBS 193 86 TYPE">
      <meta href="http://purl.org/phylo/treebase/phylows/study/TB2:S24085" id="meta3195499" rel="rdfs:isDefinedBy" xsi:type="nex:ResourceMeta"/>
    </otu>
  </otus>
  <characters about="#M49972" id="M49972" label="Neocamarosporium ITS alignment" otus="Tls68705" xml:base="http://purl.org/phylo/treebase/phylows/matrix/TB2:" xsi:type="nex:DnaSeqs">
    <meta content="Mapped from TreeBASE schema using org.cipres.treebase.domain.nexus.nexml.NexmlMatrixWriter@35a73f12 $Rev$" datatype="xsd:string" id="meta3195524" property="skos:historyNote" xsi:type="nex:LiteralMeta"/>
    <meta content="49972" datatype="xsd:long" id="meta3195523" property="tb:identifier.matrix" xsi:type="nex:LiteralMeta"/>
    <meta content="598" datatype="xsd:integer" id="meta3195522" property="tb:nchar.matrix" xsi:type="nex:LiteralMeta"/>
    <meta content="39" datatype="xsd:integer" id="meta3195521" property="tb:ntax.matrix" xsi:type="nex:LiteralMeta"/>
    <meta content="DNA" datatype="xsd:string" id="meta3195520" property="tb:type.matrix" xsi:type="nex:LiteralMeta"/>
    <format>
      <states id="states3195501">
        <state id="state3195502" symbol="A"/>
        <state id="state3195503" symbol="C"/>
        <state id="state3195504" symbol="G"/>
        <state id="state3195505" symbol="T"/>
        <uncertain_state_set id="uncertain_state_set3195506" symbol="K">
          <member state="state3195505"/>
          <member state="state3195504"/>
        </uncertain_state_set>
        <uncertain_state_set id="uncertain_state_set3195507" symbol="M">
          <member state="state3195503"/>
          <member state="state3195502"/>
        </uncertain_state_set>
        <uncertain_state_set id="uncertain_state_set3195508" symbol="R">
          <member state="state3195502"/>
          <member state="state3195504"/>
        </uncertain_state_set>
        <uncertain_state_set id="uncertain_state_set3195509" symbol="S">
          <member state="state3195503"/>
          <member state="state3195504"/>
        </uncertain_state_set>
        <uncertain_state_set id="uncertain_state_set3195510" symbol="W">
          <member state="state3195502"/>
          <member state="state3195505"/>
        </uncertain_state_set>
        <uncertain_state_set id="uncertain_state_set3195511" symbol="Y">
          <member state="state3195503"/>
          <member state="state3195505"/>
        </uncertain_state_set>
        <uncertain_state_set id="uncertain_state_set3195512" symbol="B">
          <member state="state3195503"/>
          <member state="state3195505"/>
          <member state="state3195504"/>
        </uncertain_state_set>
        <uncertain_state_set id="uncertain_state_set3195513" symbol="D">
          <member state="state3195502"/>
          <member state="state3195505"/>
          <member state="state3195504"/>
        </uncertain_state_set>
        <uncertain_state_set id="uncertain_state_set3195514" symbol="H">
          <member state="state3195502"/>
          <member state="state3195505"/>
          <member state="state3195504"/>
        </uncertain_state_set>
        <uncertain_state_set id="uncertain_state_set3195515" symbol="V">
          <member state="state3195503"/>
          <member state="state3195502"/>
          <member state="state3195504"/>
        </uncertain_state_set>
        <uncertain_state_set id="uncertain_state_set3195516" symbol="N">
          <member state="state3195502"/>
          <member state="state3195505"/>
          <member state="state3195504"/>
          <member state="state3195503"/>
        </uncertain_state_set>
        <uncertain_state_set id="uncertain_state_set3195517" symbol="X">
          <member state="state3195502"/>
          <member state="state3195505"/>
          <member state="state3195504"/>
          <member state="state3195503"/>
        </uncertain_state_set>
        <uncertain_state_set id="uncertain_state_set3195518" symbol="-"/>
        <uncertain_state_set id="uncertain_state_set3195519" symbol="?">
          <member state="state3195502"/>
          <member state="state3195504"/>
          <member state="uncertain_state_set3195518"/>
          <member state="state3195505"/>
          <member state="state3195503"/>
        </uncertain_state_set>
      </states>
      <char id="Col437713576" label="DNA" states="states3195501"/>
      <char id="Col437713577" label="DNA" states="states3195501"/>
      <char id="Col437713578" label="DNA" states="states3195501"/>
      <char id="Col437713579" label="DNA" states="states3195501"/>
      <char id="Col437713580" label="DNA" states="states3195501"/>
      <char id="Col437713581" label="DNA" states="states3195501"/>
      <char id="Col437713582" label="DNA" states="states3195501"/>
      <char id="Col437713583" label="DNA" states="states3195501"/>
      <char id="Col437713584" label="DNA" states="states3195501"/>
      <char id="Col437713585" label="DNA" states="states3195501"/>
      <char id="Col437713586" label="DNA" states="states3195501"/>
      <char id="Col437713587" label="DNA" states="states3195501"/>
      <char id="Col437713588" label="DNA" states="states3195501"/>
      <char id="Col437713589" label="DNA" states="states3195501"/>
      <char id="Col437713590" label="DNA" states="states3195501"/>
      <char id="Col437713591" label="DNA" states="states3195501"/>
      <char id="Col437713592" label="DNA" states="states3195501"/>
      <char id="Col437713593" label="DNA" states="states3195501"/>
      <char id="Col437713594" label="DNA" states="states3195501"/>
      <char id="Col437713595" label="DNA" states="states3195501"/>
      <char id="Col437713596" label="DNA" states="states3195501"/>
      <char id="Col437713597" label="DNA" states="states3195501"/>
      <char id="Col437713598" label="DNA" states="states3195501"/>
      <char id="Col437713599" label="DNA" states="states3195501"/>
      <char id="Col437713600" label="DNA" states="states3195501"/>
      <char id="Col437713601" label="DNA" states="states3195501"/>
      <char id="Col437713602" label="DNA" states="states3195501"/>
      <char id="Col437713603" label="DNA" states="states3195501"/>
      <char id="Col437713604" label="DNA" states="states3195501"/>
      <char id="Col437713605" label="DNA" states="states3195501"/>
      <char id="Col437713606" label="DNA" states="states3195501"/>
      <char id="Col437713607" label="DNA" states="states3195501"/>
      <char id="Col437713608" label="DNA" states="states3195501"/>
      <char id="Col437713609" label="DNA" states="states3195501"/>
      <char id="Col437713610" label="DNA" states="states3195501"/>
      <char id="Col437713611" label="DNA" states="states3195501"/>
      <char id="Col437713612" label="DNA" states="states3195501"/>
      <char id="Col437713613" label="DNA" states="states3195501"/>
      <char id="Col437713614" label="DNA" states="states3195501"/>
      <char id="Col437713615" label="DNA" states="states3195501"/>
      <char id="Col437713616" label="DNA" states="states3195501"/>
      <char id="Col437713617" label="DNA" states="states3195501"/>
      <char id="Col437713618" label="DNA" states="states3195501"/>
      <char id="Col437713619" label="DNA" states="states3195501"/>
      <char id="Col437713620" label="DNA" states="states3195501"/>
      <char id="Col437713621" label="DNA" states="states3195501"/>
      <char id="Col437713622" label="DNA" states="states3195501"/>
      <char id="Col437713623" label="DNA" states="states3195501"/>
      <char id="Col437713624" label="DNA" states="states3195501"/>
      <char id="Col437713625" label="DNA" states="states3195501"/>
      <char id="Col437713626" label="DNA" states="states3195501"/>
      <char id="Col437713627" label="DNA" states="states3195501"/>
      <char id="Col437713628" label="DNA" states="states3195501"/>
      <char id="Col437713629" label="DNA" states="states3195501"/>
      <char id="Col437713630" label="DNA" states="states3195501"/>
      <char id="Col437713631" label="DNA" states="states3195501"/>
      <char id="Col437713632" label="DNA" states="states3195501"/>
      <char id="Col437713633" label="DNA" states="states3195501"/>
      <char id="Col437713634" label="DNA" states="states3195501"/>
      <char id="Col437713635" label="DNA" states="states3195501"/>
      <char id="Col437713636" label="DNA" states="states3195501"/>
      <char id="Col437713637" label="DNA" states="states3195501"/>
      <char id="Col437713638" label="DNA" states="states3195501"/>
      <char id="Col437713639" label="DNA" states="states3195501"/>
      <char id="Col437713640" label="DNA" states="states3195501"/>
      <char id="Col437713641" label="DNA" states="states3195501"/>
      <char id="Col437713642" label="DNA" states="states3195501"/>
      <char id="Col437713643" label="DNA" states="states3195501"/>
      <char id="Col437713644" label="DNA" states="states3195501"/>
      <char id="Col437713645" label="DNA" states="states3195501"/>
      <char id="Col437713646" label="DNA" states="states3195501"/>
      <char id="Col437713647" label="DNA" states="states3195501"/>
      <char id="Col437713648" label="DNA" states="states3195501"/>
      <char id="Col437713649" label="DNA" states="states3195501"/>
      <char id="Col437713650" label="DNA" states="states3195501"/>
      <char id="Col437713651" label="DNA" states="states3195501"/>
      <char id="Col437713652" label="DNA" states="states3195501"/>
      <char id="Col437713653" label="DNA" states="states3195501"/>
      <char id="Col437713654" label="DNA" states="states3195501"/>
      <char id="Col437713655" label="DNA" states="states3195501"/>
      <char id="Col437713656" label="DNA" states="states3195501"/>
      <char id="Col437713657" label="DNA" states="states3195501"/>
      <char id="Col437713658" label="DNA" states="states3195501"/>
      <char id="Col437713659" label="DNA" states="states3195501"/>
      <char id="Col437713660" label="DNA" states="states3195501"/>
      <char id="Col437713661" label="DNA" states="states3195501"/>
      <char id="Col437713662" label="DNA" states="states3195501"/>
      <char id="Col437713663" label="DNA" states="states3195501"/>
      <char id="Col437713664" label="DNA" states="states3195501"/>
      <char id="Col437713665" label="DNA" states="states3195501"/>
      <char id="Col437713666" label="DNA" states="states3195501"/>
      <char id="Col437713667" label="DNA" states="states3195501"/>
      <char id="Col437713668" label="DNA" states="states3195501"/>
      <char id="Col437713669" label="DNA" states="states3195501"/>
      <char id="Col437713670" label="DNA" states="states3195501"/>
      <char id="Col437713671" label="DNA" states="states3195501"/>
      <char id="Col437713672" label="DNA" states="states3195501"/>
      <char id="Col437713673" label="DNA" states="states3195501"/>
      <char id="Col437713674" label="DNA" states="states3195501"/>
      <char id="Col437713675" label="DNA" states="states3195501"/>
      <char id="Col437713676" label="DNA" states="states3195501"/>
      <char id="Col437713677" label="DNA" states="states3195501"/>
      <char id="Col437713678" label="DNA" states="states3195501"/>
      <char id="Col437713679" label="DNA" states="states3195501"/>
      <char id="Col437713680" label="DNA" states="states3195501"/>
      <char id="Col437713681" label="DNA" states="states3195501"/>
      <char id="Col437713682" label="DNA" states="states3195501"/>
      <char id="Col437713683" label="DNA" states="states3195501"/>
      <char id="Col437713684" label="DNA" states="states3195501"/>
      <char id="Col437713685" label="DNA" states="states3195501"/>
      <char id="Col437713686" label="DNA" states="states3195501"/>
      <char id="Col437713687" label="DNA" states="states3195501"/>
      <char id="Col437713688" label="DNA" states="states3195501"/>
      <char id="Col437713689" label="DNA" states="states3195501"/>
      <char id="Col437713690" label="DNA" states="states3195501"/>
      <char id="Col437713691" label="DNA" states="states3195501"/>
      <char id="Col437713692" label="DNA" states="states3195501"/>
      <char id="Col437713693" label="DNA" states="states3195501"/>
      <char id="Col437713694" label="DNA" states="states3195501"/>
      <char id="Col437713695" label="DNA" states="states3195501"/>
      <char id="Col437713696" label="DNA" states="states3195501"/>
      <char id="Col437713697" label="DNA" states="states3195501"/>
      <char id="Col437713698" label="DNA" states="states3195501"/>
      <char id="Col437713699" label="DNA" states="states3195501"/>
      <char id="Col437713700" label="DNA" states="states3195501"/>
      <char id="Col437713701" label="DNA" states="states3195501"/>
      <char id="Col437713702" label="DNA" states="states3195501"/>
      <char id="Col437713703" label="DNA" states="states3195501"/>
      <char id="Col437713704" label="DNA" states="states3195501"/>
      <char id="Col437713705" label="DNA" states="states3195501"/>
      <char id="Col437713706" label="DNA" states="states3195501"/>
      <char id="Col437713707" label="DNA" states="states3195501"/>
      <char id="Col437713708" label="DNA" states="states3195501"/>
      <char id="Col437713709" label="DNA" states="states3195501"/>
      <char id="Col437713710" label="DNA" states="states3195501"/>
      <char id="Col437713711" label="DNA" states="states3195501"/>
      <char id="Col437713712" label="DNA" states="states3195501"/>
      <char id="Col437713713" label="DNA" states="states3195501"/>
      <char id="Col437713714" label="DNA" states="states3195501"/>
      <char id="Col437713715" label="DNA" states="states3195501"/>
      <char id="Col437713716" label="DNA" states="states3195501"/>
      <char id="Col437713717" label="DNA" states="states3195501"/>
      <char id="Col437713718" label="DNA" states="states3195501"/>
      <char id="Col437713719" label="DNA" states="states3195501"/>
      <char id="Col437713720" label="DNA" states="states3195501"/>
      <char id="Col437713721" label="DNA" states="states3195501"/>
      <char id="Col437713722" label="DNA" states="states3195501"/>
      <char id="Col437713723" label="DNA" states="states3195501"/>
      <char id="Col437713724" label="DNA" states="states3195501"/>
      <char id="Col437713725" label="DNA" states="states3195501"/>
      <char id="Col437713726" label="DNA" states="states3195501"/>
      <char id="Col437713727" label="DNA" states="states3195501"/>
      <char id="Col437713728" label="DNA" states="states3195501"/>
      <char id="Col437713729" label="DNA" states="states3195501"/>
      <char id="Col437713730" label="DNA" states="states3195501"/>
      <char id="Col437713731" label="DNA" states="states3195501"/>
      <char id="Col437713732" label="DNA" states="states3195501"/>
      <char id="Col437713733" label="DNA" states="states3195501"/>
      <char id="Col437713734" label="DNA" states="states3195501"/>
      <char id="Col437713735" label="DNA" states="states3195501"/>
      <char id="Col437713736" label="DNA" states="states3195501"/>
      <char id="Col437713737" label="DNA" states="states3195501"/>
      <char id="Col437713738" label="DNA" states="states3195501"/>
      <char id="Col437713739" label="DNA" states="states3195501"/>
      <char id="Col437713740" label="DNA" states="states3195501"/>
      <char id="Col437713741" label="DNA" states="states3195501"/>
      <char id="Col437713742" label="DNA" states="states3195501"/>
      <char id="Col437713743" label="DNA" states="states3195501"/>
      <char id="Col437713744" label="DNA" states="states3195501"/>
      <char id="Col437713745" label="DNA" states="states3195501"/>
      <char id="Col437713746" label="DNA" states="states3195501"/>
      <char id="Col437713747" label="DNA" states="states3195501"/>
      <char id="Col437713748" label="DNA" states="states3195501"/>
      <char id="Col437713749" label="DNA" states="states3195501"/>
      <char id="Col437713750" label="DNA" states="states3195501"/>
      <char id="Col437713751" label="DNA" states="states3195501"/>
      <char id="Col437713752" label="DNA" states="states3195501"/>
      <char id="Col437713753" label="DNA" states="states3195501"/>
      <char id="Col437713754" label="DNA" states="states3195501"/>
      <char id="Col437713755" label="DNA" states="states3195501"/>
      <char id="Col437713756" label="DNA" states="states3195501"/>
      <char id="Col437713757" label="DNA" states="states3195501"/>
      <char id="Col437713758" label="DNA" states="states3195501"/>
      <char id="Col437713759" label="DNA" states="states3195501"/>
      <char id="Col437713760" label="DNA" states="states3195501"/>
      <char id="Col437713761" label="DNA" states="states3195501"/>
      <char id="Col437713762" label="DNA" states="states3195501"/>
      <char id="Col437713763" label="DNA" states="states3195501"/>
      <char id="Col437713764" label="DNA" states="states3195501"/>
      <char id="Col437713765" label="DNA" states="states3195501"/>
      <char id="Col437713766" label="DNA" states="states3195501"/>
      <char id="Col437713767" label="DNA" states="states3195501"/>
      <char id="Col437713768" label="DNA" states="states3195501"/>
      <char id="Col437713769" label="DNA" states="states3195501"/>
      <char id="Col437713770" label="DNA" states="states3195501"/>
      <char id="Col437713771" label="DNA" states="states3195501"/>
      <char id="Col437713772" label="DNA" states="states3195501"/>
      <char id="Col437713773" label="DNA" states="states3195501"/>
      <char id="Col437713774" label="DNA" states="states3195501"/>
      <char id="Col437713775" label="DNA" states="states3195501"/>
      <char id="Col437713776" label="DNA" states="states3195501"/>
      <char id="Col437713777" label="DNA" states="states3195501"/>
      <char id="Col437713778" label="DNA" states="states3195501"/>
      <char id="Col437713779" label="DNA" states="states3195501"/>
      <char id="Col437713780" label="DNA" states="states3195501"/>
      <char id="Col437713781" label="DNA" states="states3195501"/>
      <char id="Col437713782" label="DNA" states="states3195501"/>
      <char id="Col437713783" label="DNA" states="states3195501"/>
      <char id="Col437713784" label="DNA" states="states3195501"/>
      <char id="Col437713785" label="DNA" states="states3195501"/>
      <char id="Col437713786" label="DNA" states="states3195501"/>
      <char id="Col437713787" label="DNA" states="states3195501"/>
      <char id="Col437713788" label="DNA" states="states3195501"/>
      <char id="Col437713789" label="DNA" states="states3195501"/>
      <char id="Col437713790" label="DNA" states="states3195501"/>
      <char id="Col437713791" label="DNA" states="states3195501"/>
      <char id="Col437713792" label="DNA" states="states3195501"/>
      <char id="Col437713793" label="DNA" states="states3195501"/>
      <char id="Col437713794" label="DNA" states="states3195501"/>
      <char id="Col437713795" label="DNA" states="states3195501"/>
      <char id="Col437713796" label="DNA" states="states3195501"/>
      <char id="Col437713797" label="DNA" states="states3195501"/>
      <char id="Col437713798" label="DNA" states="states3195501"/>
      <char id="Col437713799" label="DNA" states="states3195501"/>
      <char id="Col437713800" label="DNA" states="states3195501"/>
      <char id="Col437713801" label="DNA" states="states3195501"/>
      <char id="Col437713802" label="DNA" states="states3195501"/>
      <char id="Col437713803" label="DNA" states="states3195501"/>
      <char id="Col437713804" label="DNA" states="states3195501"/>
      <char id="Col437713805" label="DNA" states="states3195501"/>
      <char id="Col437713806" label="DNA" states="states3195501"/>
      <char id="Col437713807" label="DNA" states="states3195501"/>
      <char id="Col437713808" label="DNA" states="states3195501"/>
      <char id="Col437713809" label="DNA" states="states3195501"/>
      <char id="Col437713810" label="DNA" states="states3195501"/>
      <char id="Col437713811" label="DNA" states="states3195501"/>
      <char id="Col437713812" label="DNA" states="states3195501"/>
      <char id="Col437713813" label="DNA" states="states3195501"/>
      <char id="Col437713814" label="DNA" states="states3195501"/>
      <char id="Col437713815" label="DNA" states="states3195501"/>
      <char id="Col437713816" label="DNA" states="states3195501"/>
      <char id="Col437713817" label="DNA" states="states3195501"/>
      <char id="Col437713818" label="DNA" states="states3195501"/>
      <char id="Col437713819" label="DNA" states="states3195501"/>
      <char id="Col437713820" label="DNA" states="states3195501"/>
      <char id="Col437713821" label="DNA" states="states3195501"/>
      <char id="Col437713822" label="DNA" states="states3195501"/>
      <char id="Col437713823" label="DNA" states="states3195501"/>
      <char id="Col437713824" label="DNA" states="states3195501"/>
      <char id="Col437713825" label="DNA" states="states3195501"/>
      <char id="Col437713826" label="DNA" states="states3195501"/>
      <char id="Col437713827" label="DNA" states="states3195501"/>
      <char id="Col437713828" label="DNA" states="states3195501"/>
      <char id="Col437713829" label="DNA" states="states3195501"/>
      <char id="Col437713830" label="DNA" states="states3195501"/>
      <char id="Col437713831" label="DNA" states="states3195501"/>
      <char id="Col437713832" label="DNA" states="states3195501"/>
      <char id="Col437713833" label="DNA" states="states3195501"/>
      <char id="Col437713834" label="DNA" states="states3195501"/>
      <char id="Col437713835" label="DNA" states="states3195501"/>
      <char id="Col437713836" label="DNA" states="states3195501"/>
      <char id="Col437713837" label="DNA" states="states3195501"/>
      <char id="Col437713838" label="DNA" states="states3195501"/>
      <char id="Col437713839" label="DNA" states="states3195501"/>
      <char id="Col437713840" label="DNA" states="states3195501"/>
      <char id="Col437713841" label="DNA" states="states3195501"/>
      <char id="Col437713842" label="DNA" states="states3195501"/>
      <char id="Col437713843" label="DNA" states="states3195501"/>
      <char id="Col437713844" label="DNA" states="states3195501"/>
      <char id="Col437713845" label="DNA" states="states3195501"/>
      <char id="Col437713846" label="DNA" states="states3195501"/>
      <char id="Col437713847" label="DNA" states="states3195501"/>
      <char id="Col437713848" label="DNA" states="states3195501"/>
      <char id="Col437713849" label="DNA" states="states3195501"/>
      <char id="Col437713850" label="DNA" states="states3195501"/>
      <char id="Col437713851" label="DNA" states="states3195501"/>
      <char id="Col437713852" label="DNA" states="states3195501"/>
      <char id="Col437713853" label="DNA" states="states3195501"/>
      <char id="Col437713854" label="DNA" states="states3195501"/>
      <char id="Col437713855" label="DNA" states="states3195501"/>
      <char id="Col437713856" label="DNA" states="states3195501"/>
      <char id="Col437713857" label="DNA" states="states3195501"/>
      <char id="Col437713858" label="DNA" states="states3195501"/>
      <char id="Col437713859" label="DNA" states="states3195501"/>
      <char id="Col437713860" label="DNA" states="states3195501"/>
      <char id="Col437713861" label="DNA" states="states3195501"/>
      <char id="Col437713862" label="DNA" states="states3195501"/>
      <char id="Col437713863" label="DNA" states="states3195501"/>
      <char id="Col437713864" label="DNA" states="states3195501"/>
      <char id="Col437713865" label="DNA" states="states3195501"/>
      <char id="Col437713866" label="DNA" states="states3195501"/>
      <char id="Col437713867" label="DNA" states="states3195501"/>
      <char id="Col437713868" label="DNA" states="states3195501"/>
      <char id="Col437713869" label="DNA" states="states3195501"/>
      <char id="Col437713870" label="DNA" states="states3195501"/>
      <char id="Col437713871" label="DNA" states="states3195501"/>
      <char id="Col437713872" label="DNA" states="states3195501"/>
      <char id="Col437713873" label="DNA" states="states3195501"/>
      <char id="Col437713874" label="DNA" states="states3195501"/>
      <char id="Col437713875" label="DNA" states="states3195501"/>
      <char id="Col437713876" label="DNA" states="states3195501"/>
      <char id="Col437713877" label="DNA" states="states3195501"/>
      <char id="Col437713878" label="DNA" states="states3195501"/>
      <char id="Col437713879" label="DNA" states="states3195501"/>
      <char id="Col437713880" label="DNA" states="states3195501"/>
      <char id="Col437713881" label="DNA" states="states3195501"/>
      <char id="Col437713882" label="DNA" states="states3195501"/>
      <char id="Col437713883" label="DNA" states="states3195501"/>
      <char id="Col437713884" label="DNA" states="states3195501"/>
      <char id="Col437713885" label="DNA" states="states3195501"/>
      <char id="Col437713886" label="DNA" states="states3195501"/>
      <char id="Col437713887" label="DNA" states="states3195501"/>
      <char id="Col437713888" label="DNA" states="states3195501"/>
      <char id="Col437713889" label="DNA" states="states3195501"/>
      <char id="Col437713890" label="DNA" states="states3195501"/>
      <char id="Col437713891" label="DNA" states="states3195501"/>
      <char id="Col437713892" label="DNA" states="states3195501"/>
      <char id="Col437713893" label="DNA" states="states3195501"/>
      <char id="Col437713894" label="DNA" states="states3195501"/>
      <char id="Col437713895" label="DNA" states="states3195501"/>
      <char id="Col437713896" label="DNA" states="states3195501"/>
      <char id="Col437713897" label="DNA" states="states3195501"/>
      <char id="Col437713898" label="DNA" states="states3195501"/>
      <char id="Col437713899" label="DNA" states="states3195501"/>
      <char id="Col437713900" label="DNA" states="states3195501"/>
      <char id="Col437713901" label="DNA" states="states3195501"/>
      <char id="Col437713902" label="DNA" states="states3195501"/>
      <char id="Col437713903" label="DNA" states="states3195501"/>
      <char id="Col437713904" label="DNA" states="states3195501"/>
      <char id="Col437713905" label="DNA" states="states3195501"/>
      <char id="Col437713906" label="DNA" states="states3195501"/>
      <char id="Col437713907" label="DNA" states="states3195501"/>
      <char id="Col437713908" label="DNA" states="states3195501"/>
      <char id="Col437713909" label="DNA" states="states3195501"/>
      <char id="Col437713910" label="DNA" states="states3195501"/>
      <char id="Col437713911" label="DNA" states="states3195501"/>
      <char id="Col437713912" label="DNA" states="states3195501"/>
      <char id="Col437713913" label="DNA" states="states3195501"/>
      <char id="Col437713914" label="DNA" states="states3195501"/>
      <char id="Col437713915" label="DNA" states="states3195501"/>
      <char id="Col437713916" label="DNA" states="states3195501"/>
      <char id="Col437713917" label="DNA" states="states3195501"/>
      <char id="Col437713918" label="DNA" states="states3195501"/>
      <char id="Col437713919" label="DNA" states="states3195501"/>
      <char id="Col437713920" label="DNA" states="states3195501"/>
      <char id="Col437713921" label="DNA" states="states3195501"/>
      <char id="Col437713922" label="DNA" states="states3195501"/>
      <char id="Col437713923" label="DNA" states="states3195501"/>
      <char id="Col437713924" label="DNA" states="states3195501"/>
      <char id="Col437713925" label="DNA" states="states3195501"/>
      <char id="Col437713926" label="DNA" states="states3195501"/>
      <char id="Col437713927" label="DNA" states="states3195501"/>
      <char id="Col437713928" label="DNA" states="states3195501"/>
      <char id="Col437713929" label="DNA" states="states3195501"/>
      <char id="Col437713930" label="DNA" states="states3195501"/>
      <char id="Col437713931" label="DNA" states="states3195501"/>
      <char id="Col437713932" label="DNA" states="states3195501"/>
      <char id="Col437713933" label="DNA" states="states3195501"/>
      <char id="Col437713934" label="DNA" states="states3195501"/>
      <char id="Col437713935" label="DNA" states="states3195501"/>
      <char id="Col437713936" label="DNA" states="states3195501"/>
      <char id="Col437713937" label="DNA" states="states3195501"/>
      <char id="Col437713938" label="DNA" states="states3195501"/>
      <char id="Col437713939" label="DNA" states="states3195501"/>
      <char id="Col437713940" label="DNA" states="states3195501"/>
      <char id="Col437713941" label="DNA" states="states3195501"/>
      <char id="Col437713942" label="DNA" states="states3195501"/>
      <char id="Col437713943" label="DNA" states="states3195501"/>
      <char id="Col437713944" label="DNA" states="states3195501"/>
      <char id="Col437713945" label="DNA" states="states3195501"/>
      <char id="Col437713946" label="DNA" states="states3195501"/>
      <char id="Col437713947" label="DNA" states="states3195501"/>
      <char id="Col437713948" label="DNA" states="states3195501"/>
      <char id="Col437713949" label="DNA" states="states3195501"/>
      <char id="Col437713950" label="DNA" states="states3195501"/>
      <char id="Col437713951" label="DNA" states="states3195501"/>
      <char id="Col437713952" label="DNA" states="states3195501"/>
      <char id="Col437713953" label="DNA" states="states3195501"/>
      <char id="Col437713954" label="DNA" states="states3195501"/>
      <char id="Col437713955" label="DNA" states="states3195501"/>
      <char id="Col437713956" label="DNA" states="states3195501"/>
      <char id="Col437713957" label="DNA" states="states3195501"/>
      <char id="Col437713958" label="DNA" states="states3195501"/>
      <char id="Col437713959" label="DNA" states="states3195501"/>
      <char id="Col437713960" label="DNA" states="states3195501"/>
      <char id="Col437713961" label="DNA" states="states3195501"/>
      <char id="Col437713962" label="DNA" states="states3195501"/>
      <char id="Col437713963" label="DNA" states="states3195501"/>
      <char id="Col437713964" label="DNA" states="states3195501"/>
      <char id="Col437713965" label="DNA" states="states3195501"/>
      <char id="Col437713966" label="DNA" states="states3195501"/>
      <char id="Col437713967" label="DNA" states="states3195501"/>
      <char id="Col437713968" label="DNA" states="states3195501"/>
      <char id="Col437713969" label="DNA" states="states3195501"/>
      <char id="Col437713970" label="DNA" states="states3195501"/>
      <char id="Col437713971" label="DNA" states="states3195501"/>
      <char id="Col437713972" label="DNA" states="states3195501"/>
      <char id="Col437713973" label="DNA" states="states3195501"/>
      <char id="Col437713974" label="DNA" states="states3195501"/>
      <char id="Col437713975" label="DNA" states="states3195501"/>
      <char id="Col437713976" label="DNA" states="states3195501"/>
      <char id="Col437713977" label="DNA" states="states3195501"/>
      <char id="Col437713978" label="DNA" states="states3195501"/>
      <char id="Col437713979" label="DNA" states="states3195501"/>
      <char id="Col437713980" label="DNA" states="states3195501"/>
      <char id="Col437713981" label="DNA" states="states3195501"/>
      <char id="Col437713982" label="DNA" states="states3195501"/>
      <char id="Col437713983" label="DNA" states="states3195501"/>
      <char id="Col437713984" label="DNA" states="states3195501"/>
      <char id="Col437713985" label="DNA" states="states3195501"/>
      <char id="Col437713986" label="DNA" states="states3195501"/>
      <char id="Col437713987" label="DNA" states="states3195501"/>
      <char id="Col437713988" label="DNA" states="states3195501"/>
      <char id="Col437713989" label="DNA" states="states3195501"/>
      <char id="Col437713990" label="DNA" states="states3195501"/>
      <char id="Col437713991" label="DNA" states="states3195501"/>
      <char id="Col437713992" label="DNA" states="states3195501"/>
      <char id="Col437713993" label="DNA" states="states3195501"/>
      <char id="Col437713994" label="DNA" states="states3195501"/>
      <char id="Col437713995" label="DNA" states="states3195501"/>
      <char id="Col437713996" label="DNA" states="states3195501"/>
      <char id="Col437713997" label="DNA" states="states3195501"/>
      <char id="Col437713998" label="DNA" states="states3195501"/>
      <char id="Col437713999" label="DNA" states="states3195501"/>
      <char id="Col437714000" label="DNA" states="states3195501"/>
      <char id="Col437714001" label="DNA" states="states3195501"/>
      <char id="Col437714002" label="DNA" states="states3195501"/>
      <char id="Col437714003" label="DNA" states="states3195501"/>
      <char id="Col437714004" label="DNA" states="states3195501"/>
      <char id="Col437714005" label="DNA" states="states3195501"/>
      <char id="Col437714006" label="DNA" states="states3195501"/>
      <char id="Col437714007" label="DNA" states="states3195501"/>
      <char id="Col437714008" label="DNA" states="states3195501"/>
      <char id="Col437714009" label="DNA" states="states3195501"/>
      <char id="Col437714010" label="DNA" states="states3195501"/>
      <char id="Col437714011" label="DNA" states="states3195501"/>
      <char id="Col437714012" label="DNA" states="states3195501"/>
      <char id="Col437714013" label="DNA" states="states3195501"/>
      <char id="Col437714014" label="DNA" states="states3195501"/>
      <char id="Col437714015" label="DNA" states="states3195501"/>
      <char id="Col437714016" label="DNA" states="states3195501"/>
      <char id="Col437714017" label="DNA" states="states3195501"/>
      <char id="Col437714018" label="DNA" states="states3195501"/>
      <char id="Col437714019" label="DNA" states="states3195501"/>
      <char id="Col437714020" label="DNA" states="states3195501"/>
      <char id="Col437714021" label="DNA" states="states3195501"/>
      <char id="Col437714022" label="DNA" states="states3195501"/>
      <char id="Col437714023" label="DNA" states="states3195501"/>
      <char id="Col437714024" label="DNA" states="states3195501"/>
      <char id="Col437714025" label="DNA" states="states3195501"/>
      <char id="Col437714026" label="DNA" states="states3195501"/>
      <char id="Col437714027" label="DNA" states="states3195501"/>
      <char id="Col437714028" label="DNA" states="states3195501"/>
      <char id="Col437714029" label="DNA" states="states3195501"/>
      <char id="Col437714030" label="DNA" states="states3195501"/>
      <char id="Col437714031" label="DNA" states="states3195501"/>
      <char id="Col437714032" label="DNA" states="states3195501"/>
      <char id="Col437714033" label="DNA" states="states3195501"/>
      <char id="Col437714034" label="DNA" states="states3195501"/>
      <char id="Col437714035" label="DNA" states="states3195501"/>
      <char id="Col437714036" label="DNA" states="states3195501"/>
      <char id="Col437714037" label="DNA" states="states3195501"/>
      <char id="Col437714038" label="DNA" states="states3195501"/>
      <char id="Col437714039" label="DNA" states="states3195501"/>
      <char id="Col437714040" label="DNA" states="states3195501"/>
      <char id="Col437714041" label="DNA" states="states3195501"/>
      <char id="Col437714042" label="DNA" states="states3195501"/>
      <char id="Col437714043" label="DNA" states="states3195501"/>
      <char id="Col437714044" label="DNA" states="states3195501"/>
      <char id="Col437714045" label="DNA" states="states3195501"/>
      <char id="Col437714046" label="DNA" states="states3195501"/>
      <char id="Col437714047" label="DNA" states="states3195501"/>
      <char id="Col437714048" label="DNA" states="states3195501"/>
      <char id="Col437714049" label="DNA" states="states3195501"/>
      <char id="Col437714050" label="DNA" states="states3195501"/>
      <char id="Col437714051" label="DNA" states="states3195501"/>
      <char id="Col437714052" label="DNA" states="states3195501"/>
      <char id="Col437714053" label="DNA" states="states3195501"/>
      <char id="Col437714054" label="DNA" states="states3195501"/>
      <char id="Col437714055" label="DNA" states="states3195501"/>
      <char id="Col437714056" label="DNA" states="states3195501"/>
      <char id="Col437714057" label="DNA" states="states3195501"/>
      <char id="Col437714058" label="DNA" states="states3195501"/>
      <char id="Col437714059" label="DNA" states="states3195501"/>
      <char id="Col437714060" label="DNA" states="states3195501"/>
      <char id="Col437714061" label="DNA" states="states3195501"/>
      <char id="Col437714062" label="DNA" states="states3195501"/>
      <char id="Col437714063" label="DNA" states="states3195501"/>
      <char id="Col437714064" label="DNA" states="states3195501"/>
      <char id="Col437714065" label="DNA" states="states3195501"/>
      <char id="Col437714066" label="DNA" states="states3195501"/>
      <char id="Col437714067" label="DNA" states="states3195501"/>
      <char id="Col437714068" label="DNA" states="states3195501"/>
      <char id="Col437714069" label="DNA" states="states3195501"/>
      <char id="Col437714070" label="DNA" states="states3195501"/>
      <char id="Col437714071" label="DNA" states="states3195501"/>
      <char id="Col437714072" label="DNA" states="states3195501"/>
      <char id="Col437714073" label="DNA" states="states3195501"/>
      <char id="Col437714074" label="DNA" states="states3195501"/>
      <char id="Col437714075" label="DNA" states="states3195501"/>
      <char id="Col437714076" label="DNA" states="states3195501"/>
      <char id="Col437714077" label="DNA" states="states3195501"/>
      <char id="Col437714078" label="DNA" states="states3195501"/>
      <char id="Col437714079" label="DNA" states="states3195501"/>
      <char id="Col437714080" label="DNA" states="states3195501"/>
      <char id="Col437714081" label="DNA" states="states3195501"/>
      <char id="Col437714082" label="DNA" states="states3195501"/>
      <char id="Col437714083" label="DNA" states="states3195501"/>
      <char id="Col437714084" label="DNA" states="states3195501"/>
      <char id="Col437714085" label="DNA" states="states3195501"/>
      <char id="Col437714086" label="DNA" states="states3195501"/>
      <char id="Col437714087" label="DNA" states="states3195501"/>
      <char id="Col437714088" label="DNA" states="states3195501"/>
      <char id="Col437714089" label="DNA" states="states3195501"/>
      <char id="Col437714090" label="DNA" states="states3195501"/>
      <char id="Col437714091" label="DNA" states="states3195501"/>
      <char id="Col437714092" label="DNA" states="states3195501"/>
      <char id="Col437714093" label="DNA" states="states3195501"/>
      <char id="Col437714094" label="DNA" states="states3195501"/>
      <char id="Col437714095" label="DNA" states="states3195501"/>
      <char id="Col437714096" label="DNA" states="states3195501"/>
      <char id="Col437714097" label="DNA" states="states3195501"/>
      <char id="Col437714098" label="DNA" states="states3195501"/>
      <char id="Col437714099" label="DNA" states="states3195501"/>
      <char id="Col437714100" label="DNA" states="states3195501"/>
      <char id="Col437714101" label="DNA" states="states3195501"/>
      <char id="Col437714102" label="DNA" states="states3195501"/>
      <char id="Col437714103" label="DNA" states="states3195501"/>
      <char id="Col437714104" label="DNA" states="states3195501"/>
      <char id="Col437714105" label="DNA" states="states3195501"/>
      <char id="Col437714106" label="DNA" states="states3195501"/>
      <char id="Col437714107" label="DNA" states="states3195501"/>
      <char id="Col437714108" label="DNA" states="states3195501"/>
      <char id="Col437714109" label="DNA" states="states3195501"/>
      <char id="Col437714110" label="DNA" states="states3195501"/>
      <char id="Col437714111" label="DNA" states="states3195501"/>
      <char id="Col437714112" label="DNA" states="states3195501"/>
      <char id="Col437714113" label="DNA" states="states3195501"/>
      <char id="Col437714114" label="DNA" states="states3195501"/>
      <char id="Col437714115" label="DNA" states="states3195501"/>
      <char id="Col437714116" label="DNA" states="states3195501"/>
      <char id="Col437714117" label="DNA" states="states3195501"/>
      <char id="Col437714118" label="DNA" states="states3195501"/>
      <char id="Col437714119" label="DNA" states="states3195501"/>
      <char id="Col437714120" label="DNA" states="states3195501"/>
      <char id="Col437714121" label="DNA" states="states3195501"/>
      <char id="Col437714122" label="DNA" states="states3195501"/>
      <char id="Col437714123" label="DNA" states="states3195501"/>
      <char id="Col437714124" label="DNA" states="states3195501"/>
      <char id="Col437714125" label="DNA" states="states3195501"/>
      <char id="Col437714126" label="DNA" states="states3195501"/>
      <char id="Col437714127" label="DNA" states="states3195501"/>
      <char id="Col437714128" label="DNA" states="states3195501"/>
      <char id="Col437714129" label="DNA" states="states3195501"/>
      <char id="Col437714130" label="DNA" states="states3195501"/>
      <char id="Col437714131" label="DNA" states="states3195501"/>
      <char id="Col437714132" label="DNA" states="states3195501"/>
      <char id="Col437714133" label="DNA" states="states3195501"/>
      <char id="Col437714134" label="DNA" states="states3195501"/>
      <char id="Col437714135" label="DNA" states="states3195501"/>
      <char id="Col437714136" label="DNA" states="states3195501"/>
      <char id="Col437714137" label="DNA" states="states3195501"/>
      <char id="Col437714138" label="DNA" states="states3195501"/>
      <char id="Col437714139" label="DNA" states="states3195501"/>
      <char id="Col437714140" label="DNA" states="states3195501"/>
      <char id="Col437714141" label="DNA" states="states3195501"/>
      <char id="Col437714142" label="DNA" states="states3195501"/>
      <char id="Col437714143" label="DNA" states="states3195501"/>
      <char id="Col437714144" label="DNA" states="states3195501"/>
      <char id="Col437714145" label="DNA" states="states3195501"/>
      <char id="Col437714146" label="DNA" states="states3195501"/>
      <char id="Col437714147" label="DNA" states="states3195501"/>
      <char id="Col437714148" label="DNA" states="states3195501"/>
      <char id="Col437714149" label="DNA" states="states3195501"/>
      <char id="Col437714150" label="DNA" states="states3195501"/>
      <char id="Col437714151" label="DNA" states="states3195501"/>
      <char id="Col437714152" label="DNA" states="states3195501"/>
      <char id="Col437714153" label="DNA" states="states3195501"/>
      <char id="Col437714154" label="DNA" states="states3195501"/>
      <char id="Col437714155" label="DNA" states="states3195501"/>
      <char id="Col437714156" label="DNA" states="states3195501"/>
      <char id="Col437714157" label="DNA" states="states3195501"/>
      <char id="Col437714158" label="DNA" states="states3195501"/>
      <char id="Col437714159" label="DNA" states="states3195501"/>
      <char id="Col437714160" label="DNA" states="states3195501"/>
      <char id="Col437714161" label="DNA" states="states3195501"/>
      <char id="Col437714162" label="DNA" states="states3195501"/>
      <char id="Col437714163" label="DNA" states="states3195501"/>
      <char id="Col437714164" label="DNA" states="states3195501"/>
      <char id="Col437714165" label="DNA" states="states3195501"/>
      <char id="Col437714166" label="DNA" states="states3195501"/>
      <char id="Col437714167" label="DNA" states="states3195501"/>
      <char id="Col437714168" label="DNA" states="states3195501"/>
      <char id="Col437714169" label="DNA" states="states3195501"/>
      <char id="Col437714170" label="DNA" states="states3195501"/>
      <char id="Col437714171" label="DNA" states="states3195501"/>
      <char id="Col437714172" label="DNA" states="states3195501"/>
      <char id="Col437714173" label="DNA" states="states3195501"/>
    </format>
    <matrix>
      <row id="Row4268453" otu="Tl3626488">
        <seq>-----------------ATCATTAA-CCATATGAACGCAGG-TGGGGGTT-CACAAGCATA---------TTC----------GTACGCTT-GCCCTGCCTGTCCTAAT-ATCCACCCATGTTTTTT-GCGTACTATTCGTTTCCTCGGCGGGCTTGCCCGCCAGTAGGACACCATA--AAACCTTTT---GTAATTGCAGTCAGCGTCAGAAAAA-CTTTAATAGTTACAACTTTCAACAACGGATCTCTTGGTTCTGGCATCGATGAAGAACGCAGCGAAATGCGATAAGTAGTGTGAATTGCAGAATTCAGTGAATCATCGAATCTTTGAACGCACATTGCGCCCCTTGGTATTCCATGGGGCATGCCTGTTCGAGCGTCATTT-GTACCCTCAAGCTCTGCTTGGTGTTGGGCGT--TTGTCCCCTTTAC------AAGGACTCGCCTCAAAAATA-TTGGCAGCCGGCATACTGGTCTCGGAGCGCAGCACATT--TTGCGCCCCATTTCC--TGAA-TACT-GGCGTCCATGAAGCCCATATATTTTA--ACTCTTGACCTCGGATCAGGTAGGGATACC------------</seq>
      </row>
      <row id="Row4268454" otu="Tl3626495">
        <seq>----AACAAGCGGAAGGATCATTAA-CCATATGAACGCAGG-TGGGGGTT-CACAAGCATA---------TTC----------GTACGCTT-GCCCTGCCTGTCCTAAT-ATCCACCCATGCTTTTT-GCGTACTATTCGTTTCCTCGGCGGGCTTGCCCGCCAGTAGGACACCATA--AAACCTTTT---GTAATTGCAGTCAGCGTCAGAAAAA-CTTTAATAGTTACAACTTTCAACAACGGATCTCTTGGTTCTGGCATCGATGAAGAACGCAGCGAAATGCGATAAGTAGTGTGAATTGCAGAATTCAGTGAATCATCGAATCTTTGAACGCACATTGCGCCCCTTGGTATTCCATGGGGCATGCCTGTTCGAGCGTCATTT-GTACCCTCAAGCTCTGCTTGGTGTTGGGCGT--TTGTCCCCTTTAC------AAGGACTCGCCTTAAAAATA-TTGGCAGCCGGCATACTGGTCTCGGAGCGCAGCACATT--TTGCGCCCCATTTCC--TGAA-TACT-GGCGTCCATGAAGCCCACATATTTTA--ACTCTTGACCTCGGATCAGGTAGGGATACCCGCTGAACTTAA</seq>
      </row>
      <row id="Row4268455" otu="Tl3535873">
        <seq>---------GCGGAAGGATCAT-------TATCAAAACAG-------------CGGAC------------TTC----------G--------GTCCTTGCTG-----------CACCCTTGTCTTTT-GCGTACCGTATGTTTCCTCGGCGGGCTTGCCTGCCGGTTGGACATTATC--AAACCTTTTT--GTAGTTGCAATCAGCGTCAGAAAA--TAATAATAATTACAACTTTCAACAACGGATCTCTTGGTTCTGGCATCGATGAAGAACGCAGCGAAATGCGAAAAGTAGTGTGAATTGCAGAATTCAGTGAATCATCGAATCTTTGAACGCACATTGCGCCCCTTGGTATTCCATGGGGCATGCCTGTTCGAGCGTCATTTTGTACCCTCAAGCACTGCTTGGTGTTGGGCGC--TTGTC--CTGCA-------AAGGACTCGCCTGAAAGCGA-TTGGCGGCCAACGTACTGGTGGTAGAGCGCAGCACAAT--TTGCGTCTT-TCCCC--TCTG-CGTT-AGCGTCCATAAAGCC----TATTTCA--ACGTTTGACCTCGGATCAG-----------------------</seq>
      </row>
      <row id="Row4268456" otu="Tl3535853">
        <seq>-----------------ATCATTAC-CAATATGAAAGCGGG-TGGGGAGC-CACAGAAGTCG----GGGCCCTCGT--GGCTC-TACTTCT-GCCCCATCTGTCTGAAT-ATTCACCCATGTCTTTT-GCGTACCCATTGTTTCCTTGGCGGGCTTGCCCGCCAATAGGACATTGTT--AAACCTTTT---GTAATTGCAGTCAGCGTCAGAAATA-ACTTAATAGTTACAACTTTCAACAACGGATCTCTTGGTTCTGGCATCGATGAAGAACGCAGCGAAATGCGATAAGTAGTGTGAATTGCAGAATTCAGTGAATCATCGAATCTTTGAACGCACATTGCGCCCCTTGGTATTCCATGGGGCATGCCTGTTCGAGCGTCATTT-GTACCCTCAAGCTCTGCTTGGTGTTGGGTGT--TTGTCTCCCCT-------GGGAGACTCGCCTCAAAACAA-TTGGCAGCCGGCATATTGGTATCGGAGCGCAGCACAAG--TCGCGCTTC-TGTCC-ATATT-TGTT-GGCATCCAGCAAGACC---ATTTTTC--ACTCTTGACCTCGGATCAGGTAGG--GATACC----------</seq>
      </row>
      <row id="Row4268457" otu="Tl3535852">
        <seq>-----------------ATCATTAC-CAATATGAAAGCGGG-TGGGGAGC-CACAGAAGTCG----GGGCCCTCGT--GGCTC-TACTTCT-GCCCCATCTGTCTGAAT-ATTCACCCATGTCTTTT-GCGTACCCATTGTTTCCTTGGCGGGCTTGCCCGCCAATAGGACATTGTT--AAACCTTTT---GTAATTGCAGTCAGCGTCAGAAATA-ACTTAATAGTTACAACTTTCAACAACGGATCTCTTGGTTCTGGCATCGATGAAGAACGCAGCGAAATGCGATAAGTAGTGTGAATTGCAGAATTCAGTGAATCATCGAATCTTTGAACGCACATTGCGCCCCTTGGTATTCCATGGGGCATGCCTGTTCGAGCGTCATTT-GTACCCTCAAGCTCTGCTTGGTGTTGGGTGT--TTGTCTCCCCT-------GGGAGACTCGCCTCAAAACAA-TTGGCAGCCGGCATATTGGTATCGGAGCGCAGCACAAG--TCGCGCTTC-TGTCC-ATATT-TGTT-GGCATCCAGCAAGACC---ATTTTTC--ACTCTTGACCTCGGATCAGGTAGG--GATACC----------</seq>
      </row>
      <row id="Row4268458" otu="Tl3535865">
        <seq>-----------------ATCATTAC-CAATATGAAAGCGGG-TGGGGAGC-CACAGAAGTCG----GGGCCCTCGT--GGCTC-TACTTCT-GCCCCATCTGTCTGAAT-ATTCACCCATGTCTTTT-GCGTACCCATTGTTTCCTTGGCGGGCTTGCCCGCCAATAGGACATTGTT--AAACCTTTT---GTAATTGCAGTCAGCGTCAGAAATA-ACTTAATAGTTACAACTTTCAACAACGGATCTCTTGGTTCTGGCATCGATGAAGAACGCAGCGAAATGCGATAAGTAGTGTGAATTGCAGAATTCAGTGAATCATCGAATCTTTGAACGCACATTGCGCCCCTTGGTATTCCATGGGGCATGCCTGTTCGAGCGTCATTT-GTACCCTCAAGCTCTGCTTGGTGTTGGGTGT--TTGTCTCCCCT-------GGGAGACTCGCCTCAAAACAA-TTGGCAGCCGGCATATTGGTATCGGAGCGCAGCACAAG--TCGCGCTTC-TGTCC-ATATT-TGTT-GGCATCCAGCAAGACC---ATTTTTC--ACTCTTGACCTCGGATCAGGTAGG--GATACC----------</seq>
      </row>
      <row id="Row4268459" otu="Tl3535871">
        <seq>-----------------ATCATTAC-CAATATGAAAGCGGG-TGGGGAGC-CACAGAAGTCG----GGGCCCTCGT--GGCTC-TACTTCT-GCCCCATCTGTCTGAAT-ATTCACCCATGTCTTTT-GCGTACCCATTGTTTCCTTGGCGGGCTTGCCCGCCAATAGGACATTGTT--AAACCTTTT---GTAATTGCAGTCAGCGTCAGAAATA-ACTTAATAGTTACAACTTTCAACAACGGATCTCTTGGTTCTGGCATCGATGAAGAACGCAGCGAAATGCGATAAGTAGTGTGAATTGCAGAATTCAGTGAATCATCGAATCTTTGAACGCACATTGCGCCCCTTGGTATTCCATGGGGCATGCCTGTTCGAGCGTCATTT-GTACCCTCAAGCTCTGCTTGGTGTTGGGTGT--TTGTCTCCCCT-------GGGAGACTCGCCTCAAAACAA-TTGGCAGCCGGCATATTGGTATCGGAGCGCAGCACAAG--TCGCGCTTC-TGTCC-ATATT-TGTT-GGCATCCAGCAAGACC---ATTTTTC--ACTCTTGACCTCGGATCAGGTAGG--GATACC----------</seq>
      </row>
      <row id="Row4268460" otu="Tl3535870">
        <seq>-----------------ATCATTAC-CAATATGAAAGCGGG-TGGGGAGC-CACAGAAGTCG----GGGCCCTCGT--GGCTC-TACTTCT-GCCCCATCTGTCTGAAT-ATTCACCCATGTCTTTT-GCGTACCCATTGTTTCCTTGGCGGGCTTGCCCGCCAACAGGACATTATT--AAACCTTTT---GTAATTGCAGTCAGCGTCAGAAATA-ACTTAATAGTTACAACTTTCAACAACGGATCTCTTGGTTCTGGCATCGATGAAGAACGCAGCGAAATGCGATAAGTAGTGTGAATTGCAGAATTCAGTGAATCATCGAATCTTTGAACGCACATTGCGCCCCTTGGTATTCCATGGGGCATGCCTGTTCGAGCGTCATTT-GTACCCTCAAGCTCTGCTTGGTGTTGGGTGT--TTGTCTCCCCT-------GGGAGACTCGCCTCAAAACAA-TTGGCAGCCGGCATATTGGTATCGGAGCGCAGCACAAG--TCGCGCTTC-TGTCC-ATATT-TGTT-GGCATCCAGCAAGACC---ATTTTTC--ACTCTTGACCTCGGATCAGGTAGG--GATACC----------</seq>
      </row>
      <row id="Row4268461" otu="Tl3626487">
        <seq>-----------------ATCATTAC-CAATATGAAAGCGGG-TGGGGAGC-CACAGAAGCCG----GAGCCCTCGT--GGCTC-TGTTTCT-GCCCCATCTGTCTGAAT-ATTCACCCATGTCTTTT-GCGTACCAATTGTTTCCTTGGCGGGCTTGCCCGCCAACAGGACATTGTT--AAACCTTTT---GTAATTGCAGTCAGCGTCAGAAAAA-ACTTAATAGTTACAACTTTCAACAACGGATCTCTTGGTTCTGGCATCGATGAAGAACGCAGCGAAATGCGATAAGTAGTGTGAATTGCAGAATTCAGTGAATCATCGAATCTTTGAACGCACATTGCGCCCCTTGGTATTCCATGGGGCATGCCTGTTCGAGCGTCATTT-GTACCCTCAAGCTCTGCTTGGTGTTGGGCGT--TTGTCTCCCCT-------GGGAGACTCGCCTCAAAACAA-TTGGCAGCCGGCATATTGGTATCGGAGCGCAGCACAAG--TCGCGCTTC-TGTCC-ATGAA-TGTC-GGCGTCCAGCAAGATCTC-ATTTTTC--ACTCTTGACCTCCGATCACGCTGCCTGCTAC-----------</seq>
      </row>
      <row id="Row4268462" otu="Tl3535849">
        <seq>-----------------ATCATTAC-CAATATGAAAGCGGG-TGGGGAGC-CACAGAAGCAT----GAGCTCC-----GGCTTGTGCCTTT-GCCCCATCTGTCTGAAT-ATTCACCCATGTCTTTT-GCGTACTATTTGTTTCCTTGGCGGGCTTGCCCGCCAGCAGGACATTATT--AAACCTTTT---GTAATTGAAGTCAGCGTCAGAA-TA-ACTTAATAGTTACAACTTTCAACAACGGATCTCTTGGTTCTGGCATCGATGAAGAACGCAGCGAAATGCGATAAGTAGTGTGAATTGCAGAATTCAGTGAATCATCGAATCTTTGAACGCACATTGCGCCCCTTGGTATTCCATGGGGCATGCCTGTTCGAGCGTCATTT-GTACCCTCAAGCTTTGCTTGGTGTTGGGCGTC-TTGTCTCCCTCTC-----GGGAGACTCGCCTCAAAACAA-TTGGCAGCCGGCATATTGGTATCGGAGCGCAGCACAAG--TCGCGCTTC-TTTCC-ATGAA-TGTC-AGCATCCATCAAGACC---ATT------------------------------------------------</seq>
      </row>
      <row id="Row4268463" otu="Tl3535869">
        <seq>-----------------ATCATTAC-CAATATGAAAGCGGG-TGGGGAGC-CACAGAAGCAT----GAGCTCC-----GGCTTGTGCCTTT-GCCCCATCTGTCTGAAT-ATTCACCCATGTCTTTT-GCGTACTATTTGTTTCCTTGGCGGGCTTGCCCGCCAGCAGGACATTATT--AAACCTTTT---GTAATTGAAGTCAGCGTCAGAA-TA-ACTTAATAGTTACAACTTTCAACAACGGATCTCTTGGTTCTGGCATCGATGAAGAACGCAGCGAAATGCGATAAGTAGTGTGAATTGCAGAATTCAGTGAATCATCGAATCTTTGAACGCACATTGCGCCCCTTGGTATTCCATGGGGCATGCCTGTTCGAGCGTCATTT-GTACCCTCAAGCTTTGCTTGGTGTTGGGCGTC-TTGTCTCCCTCTC-----GGGAGACTCGCCTCAAAACAA-TTGGCAGCCGGCATATTGGTATCGGAGCGCAGCACAAG--TCGCGCTTC-TTTCC-ATGAA-TGTC-AGCATCCATCAAGACC---ATTTT----------------------------------------------</seq>
      </row>
      <row id="Row4268464" otu="Tl3535848">
        <seq>-----------------ATCATTAC-CAATATGAAAGCGGT-TGGGGAGC-CACAGAAGCAT----GAGCTCC-----GGCTTGTGCCTTT-GCCCCATCTGTCTGAAT-ATTCACCCATGTCTTTT-GCGTACTATTTGTTTCCTTGGCGGGCTTGCCCGCCAGCAGGACATTATT--AAACCTTTT---GTAATTGAAGTCAGCGTCAGAA-TA-ACTTAATAGTTACAACTTTCAACAACGGATCTCTTGGTTCTGGCATCGATGAAGAACGCAGCGAAATGCGATAAGTAGTGTGAATTGCAGAATTCAGTGAATCATCGAATCTTTGAACGCACATTGCGCCCCTTGGTATTCCATGGGGCATGCCTGTTCGAGCGTCATTT-GTACCCTCAAGCTTTGCTTGGTGTTGGGCGTC-TTGTCTCCCTTTT-----GGGAGACTCGCCTCAAAACAA-TTGGCAGCCGGCATATTGGTATCGGAGCGCAGCACAAG--TCGCGCTTC-TTTCC-ATGAA-TGTC-AGCATCCATCAAGACC---ATTTTTC--ACTCTTGACCTCGGATCAGGTAGG--GATACC----------</seq>
      </row>
      <row id="Row4268465" otu="Tl3535874">
        <seq>-----------------ATCATTAC-CAATATGAAAGCGGG-TGGGGAGC-CACAGAAGCAT----GAGCTCC-----GGCTTGTGCCTTT-GCCCCATCTGTCTGAAT-ATTCACCCATGTCTTTT-GCGTACTATTTGTTTCCTTGGCGGGCTTGCCCGCCAGCAGGACATTATT--AAACCTTTT---GTAATTGAAGTCAGCGTCAGAA-TA-ACTTAATAGTTACAACTTTCAACAACGGATCTCTTGGTTCTGGCATCGATGAAGAACGCAGCGAAATGCGATAAGTAGTGTGAATTGCAGAATTCAGTGAATCATCGAATCTTTGAACGCACATTGCGCCCCTTGGTATTCCATGGGGCATGCCTGTTCGAGCGTCATTT-GTACCCTCAAGCTTTGCTTGGTGTTGGGCGTC-TTGTCTCCCTTTT-----GGGAGACTCGCCTCAAAACAA-TTGGCAGCCGGCATATTGGTATCGGAGCGCAGCACAAG--TCGCGCTTC-TTTCC-ATGAA-TGTC-AGCATCCATCAAGACT---ATTTTTC--ACTCTTGACCTCGGATCAGGTAGG--GATACC----------</seq>
      </row>
      <row id="Row4268466" otu="Tl3535860">
        <seq>-----------------ATCATTAC-CAATATGAAAGCGGG-TGGGGAGC-CACAAAAGCAT----GAGCTCC-----GGCTTGTGCCTTT-GCCCCATCTGTCTGAAT-ATTCACCCATGTCTTTT-GCGTACTATTTGTTTCCTTGGCGGGCTTGCCCGCCAGCAGGACATTATT--AAACCTTTT---GTAATTGAAGTCAGCGTCAGAA-TA-ACTTAATAGTTACAACTTTCAACAACGGATCTCTTGGTTCTGGCATCGATGAAGAACGCAGCGAAATGCGATAAGTAGTGTGAATTGCAGAATTCAGTGAATCATCGAATCTTTGAACGCACATTGCGCCCCTTGGTATTCCATGGGGCATGCCTGTTCGAGCGTCATTT-GTACCCTCAAGCTTTGCTTGGTGTTGGGCGTC-TTGTCTCCCTTTT-----GGGAGACTCGCCTCAAAACAA-TTGGCAGCCGGCATATTGGTATCGGAGCGCAGCACAAG--TCGCGCTTC-TTTCC-ATGAA-TGTC-AGCATCCATCAAGACC---ATTTTTC--ACTCTTGACCTCGGATCAGGTAGG--GATACCCGCTGAACTT</seq>
      </row>
      <row id="Row4268467" otu="Tl3535863">
        <seq>-----------------ATCATTAC-CAATATGAAAGCGGG-TGGGGAGCACACAGAA-CAT----GAGCTCC-----GGCTTGTGCCTTT-GCCCCATCTGTCTGAAT-ATTCACCCATGTCTTTTTGCGTACTATTTGTTTCCTTGGCGGGCTTGCCCGCCAGCAGGACATTATTT-AAACCTTTT---GTAATTGAAGTCAGCGTCAGAA-AA-ACTTAATAGTTACAACTTTCAACAACGGATCTCTTGGTTCTGGCATCGATGAAGAACGCAGCGAAATGCGATAAGTAGTGTGAATTGCAGAATTCAGTGAATCATCGAATCTTTGAACGCACATTGCGCCCCTTGGTATTCCATGGGGCATGCCTGTTCGAGCGTCATTT-GTACCCTCAAGCTTTGCTTGGTGTTGGGCGTC-TTGTCTCCCTTTT-----GGGAGACTCGCCTCAAAACAA-TTGGCAGCCGGCATATTGGTATCGGAGCGCAGCACAAG--TCGCGCTTC-TTTCC-ATGAA-TGTC-AGCATCCATCAAGACC---ATTTTTC--ACTTTTGACCTCGGATCAGGTA--------------------</seq>
      </row>
      <row id="Row4268468" otu="Tl3535855">
        <seq>-CGTAACAAGCGGAAGGATCATTAC-CAATATGAAAGCGGG-TGGGGAAC-CACAAAAGCGC----GAGCTCC-----GGCTTGTGTTTTT-GCCCCATCTGTCTGAAT-ATTCACCCATGTCTTTT-GCGTACTATTTGTTTCCTTGGTGGGCTTGCCCACCAATAGGACATTATT--AAACCTTTT---GTAATTGCAGTCAGCGTCAGAAAAA--CTTAATAGTTACAACTTTCAACAACGGATCTCTTGGTTCTGGCATCGATGAAGAACGCAGCGAAATGCGATAAGTAGTGTGAATTGCAGAATTCAGTGAATCATCGAATCTTTGAACGCACATTGCGCCCCTTGGTATTCCATGGGGCATGCCTGTTCGAGCGTCATTT-GTACCCTCAAGCTTTGCTTGGTGTTGGGTGTT-T-GTCCTCT-CT------GGAGGACTCGCCTTAAAACAA-TTGGCAGCCGGCATATTGGTATCGGAGCGCAGCACAAG--TCGCACTTC-TTTCC-ATGAA-TGTC-AGCATCCATCAAGACC---ATTTTTC--ACTCT-GACCTCG-ATCAGGTA--------------------</seq>
      </row>
      <row id="Row4268469" otu="Tl3535850">
        <seq>ACGTAACAAGCGGAAGGATCATTAC-CAATATGAAAGCGGG-TGGGGAAC-CACAGCAATAG----GAGCTCC-----GGCTTGTGTTGCT-GCCCCATCTGTCTGAAT-ATTCACCCATGTCTTTT-GCGTACTATTTGTTTCCTTGGTGGGCTTGCCCACCAATAGGACATTATT--AAACCTTTT---GTAATTGCAGTCAGCGTCAGAAAAA--CTTAATAGTTACAACTTTCAACAACGGATCTCTTGGTTCTGGCATCGATGAAGAACGCAGCGAAATGCGATAAGTAGTGTGAATTGCAGAATTCAGTGAATCATCGAATCTTTGAACGCACATTGCGCCCCTTGGTATTCCATGGGGCATGCCTGTTCGAGCGTCATTT-GTACCCTCAAGCTTTGCTTGGTGTTGGGTGTT-T-GTCCTCT-CT------GGAGGACTCGCCTTAAAACAA-TTGGCAGCCGGCATATTGGTATCGGAGCGCAGCACAAG--TCGCGCTTC-TTTCC-ATGAA-TGTC-AGCATCCATCAAGACT---ATTTT-C--ACTCT-GACCTCGGATCAG-TA--------------------</seq>
      </row>
      <row id="Row4268470" otu="Tl3535875">
        <seq>-----------------ATCATTAC-CAATATGAAAGCGGGATGGGGAGC-CACGGCAT-------GCGCTCC-----GGCGTGTAATGCC-GCCCCATCTGGCTGACT-ATTCACCCATGTCTTTT-GCGTACCATTTGTTTCCTTGGTGGGCTTGCCCACCGATAGGACAGTATT--AAACCATTT---GCAATTGCAGTCAGCGTCAGAAAAA-ACTTAATAGTTACAACTTTCAACAACGGATCTCTTGGTTCTGGCATCGATGAAGAACGCAGCGAAATGCGATAAGTAGTGTGAATTGCAGAATTCAGTGAATCATCGAATCTTTGAACGCACATTGCGCCCCTTGGTATTCCATGGGGCATGCCTGTTCGAGCGTCATTT-GTACCCTCAAGCTTTGCTTGGTGTTGGGTGTT-T-GTCTTCCGCT------GG-AGACTCGCCTTAAAACAA-TTGGCAGCCGGCATATTGGTATCGGAGCGCAGCACAAG--TCGCGCTTC-TTTCC-ATGAA-TGTC-AGCGTCCATCAAGACC---ATTTTTC--ACTCTTGACCTCGGATCAGGTA--------------------</seq>
      </row>
      <row id="Row4268471" otu="Tl3535859">
        <seq>TCGTAACAAGCGGAAGGATCATTAC-CAATATGAAAGCGGGATGGGGAGC-CACGGCATCAG----GCGCTCC-----GGCGTGTAATGCC-GCCCCATCTGGCTGACT-ATTCACCCATGTCTTTT-GCGTACCATTTGTTTCCTTGGTGGGCTTGCCCACCGATAGGACAGTATT--AAACCATTT---GCAATTGCAGTCAGCGTCAGAAAAA-ACTTAATAGTTACAACTTTCAACAACGGATCTCTTGGTTCTGGCATCGATGAAGAACGCAGCGAAATGCGATAAGTAGTGTGAATTGCAGAATTCAGTGAATCATCGAATCTTTGAACGCACATTGCGCCCCTTGGTATTCCATGGGGCATGCCTGTTCGAGCGTCATTT-GTACCCTCAAGCTTTGCTTGGTGTTGGGTGTT-T-GTCTTCCGCT------GGGAGACTCGCCTTAAAACAA-TTGGCAGCCGGCATATTGGTATCGGAGCGCAGCACAAG--TCGCGCTTC-TTTCC-ATGAA-TGTC-AGCGTCCATCAAGACC---ATTTTTC--ACTCT-GACCTCGGATCAGG----------------------</seq>
      </row>
      <row id="Row4268472" otu="Tl3626494">
        <seq>------CAAGCGGAAGGATCATTAC-CAATATGAAAGCGGG-TGGGGAAC-CACAGCAATAG----GAGCTCC-----GGCTTGTGTTGCT-GCCCCATCTGTCTGAAT-ATTCACCCATGTCTTTT-GCGTACTATTTGTTTCCTTGGTGGGCTTGCCCACCAATAGGACATTATT--AAACCTTTT---GTAATTGCAGTCAGCGTCAGAAAAA--CTTAATAGTTACAACTTTCAACAACGGATCTCTTGGTTCTGGCATCGATGAAGAACGCAGCGAAATGCGATAAGTAGTGTGAATTGCAGAATTCAGTGAATCATCGAATCTTTGAACGCACATTGCGCCCCTTGGTATTCCATGGGGCATGCCTGTTCGAGCGTCATTT-GTACCCTCAAGCTTTGCTTGGTGTTGGGTGTT-T-GTCCTCT-CT------GGAGGACTCGCCTTAAAACAA-TTGGCAGCCGGCATATTGGTATCGGAGCGCAGCACAAG--TCGCGCTTC-TTTCC-ATGAA-TGTC-TGCATCCATCAAGACT---ATTTT-C--ACTCTTGACCTCGGATCAGGTAGGGATACCCGCTGAACTTAA</seq>
      </row>
      <row id="Row4268473" otu="Tl3535877">
        <seq>---------GCGGAAGGATCATTAC-CAATATGAAAGCGGG-TGGGGA-T-TACGG-AACAT----GGGCTTC-----GGCCTGCGTTTTT-GCCCCATCTTGCTGAATTATTCACCCATGTCTTTT-GCGTACTACTTGTTTCCTTGGTGGGCTTGCCTGCCGATAGGACAATATT--AAACCTTTT---GTAATTGCAATCAGCGTCAGAAAAC--TTTAATAGTTACAACTTTCAACAACGGATCTCTTGGTTCTGGCATCGATGAAGAACGCAGCGAAATGCGATAAGTAGTGTGAATTGCAGAATTCAGTGAATCATCGAATCTTTGAACGCACATTGCGCCCCTTGGTATTCCATGGGGCATGCCTGTTCGAGCGTCATTT-GTACCCTCAAGCTTTGCTTGGTGTTGGGCGTT-TTGTCCTCC------------GGACTCGCCTTAAAACAA-TTGGCAGCCGGCATATTGGTATCGGAGCGCAGCACAAG--TCGCACTTC-TTTCC-ATGAA-TGTT-GGCATCCATCAAGACT---ATTTTTC--ACTCT-GACCTCGGATCAGGTA--------------------</seq>
      </row>
      <row id="Row4268474" otu="Tl3535846">
        <seq>-------------------CATTAC-CAATATGAAAGCGGA-TGGGGAAC-CACGGGGACAAA--CGGGCTTC-----GGCCTGCGTTCCT-GCCCCATCTTGCTGAAT-ATTCACCCATGTCTTTT-GCGTACTATTTGTTTCCTTGGTGGGCTTGCCCACCAATAGGACAATCTT--AAACCTTTT---GTAATTGCAATCAGCGTCAGAAAAAACTTTAATAGTTACAACTTTCAACAACGGATCTCTTGGTTCTGGCATCGATGAAGAACGCAGCGAAATGCGATAAGTAGTGTGAATTGCAGAATTCAGTGAATCATCGAATCTTTGAACGCACATTGCGCCCCTTGGTATTCCATGGGGCATGCCTGTTCGAGCGTCATTT-GTACCCTCAAGCTTTGCTTGGTGTTGGGCGTA-TTGTCCTCTTTTTTTTTTAAAGGACTCGCCTCAAAACAA-TTGGCAGCCGGCCTATTGGTATCGGAGCGCAGCACAAG--TCGCGCTTC-TTTCC-ATGAAG-GTT-GACGTCCATCAAGACCA--TTTTTTC--ACTCTTGACCTCGGATCAGGTAGGGATACCCGCTGAACTTAA</seq>
      </row>
      <row id="Row4268475" otu="Tl3535876">
        <seq>----------------------------------AAGCGGA-TGGGGAAC-CACGGGGACAA---CGGGCTTC-----GGCCTGCGTTCCT-GCCCCATCTTGCTGAAT-ATTCACCCATGTCTTTT-GCGTACTATTTGTTTCCTTGGTGGGCTTGCCCACCAATAGGACAATCTT--AAACCTTTT---GTAATTGCAATCAGCGTCAGAAAAAACTTTAATAGTTACAACTTTCAACAACGGATCTCTTGGTTCTGGCATCGATGAAGAACGCAGCGAAATGCGATAAGTAGTGTGAATTGCAGAATTCAGTGAATCATCGAATCTTTGAACGCACATTGCGCCCCTTGGTATTCCATGGGGCATGCCTGTTCGAGCGTCATTT-GTACCCTCAAGCTTTGCTTGGTGTTGGGCGTA-TTGTCCTCTTTTTTTTT-AGAGGACTCGCCTCAAAACAA-TTGGCAGCCGGCCTATTGGTATCGGAGCGCAGCACAAG--TCGCGCTTC-TTTCC-ATGAAG-GTT-GACGTCCATCAAGACCA--TTTTTTC--ACTCTTGACCTCGGATCAGGTAGGGATACCCGCTGAACTTAA</seq>
      </row>
      <row id="Row4268476" otu="Tl3626493">
        <seq>-----------------------------TATGAAAGCGGA-TGGGGAAC-CACGGGAACAA---TGGGCTCC-----GGCCTGCGTTCCT-GCCCCATTTTGCTGAAT-ATTCACCCATGTCTTTT-GCGTACTATTTGTTTCCTTGGTGGGCTTGCCCACCGATAGGACAATCTT--AAACCTTTT---GTAATTGCAATCAGCGTCAGAAAAA-CTTTAATAGTTACAACTTTCAACAACGGATCTCTTGGTTCTGGCATCGATGAAGAACGCAGCGAAATGCGATAAGTAGTGTGAATTGCAGAATTCAGTGAATCATCGAATCTTTGAACGCACATTGCGCCCCTTGGTATTCCATGGGGCATGCCTGTTCGAGCGTCATTT-GTACCCTCAAGCTTTGCTTGGTGTTGGGCGTC-TTGTCCTCTTTTC------GAGGACTCGCCTCAAAACAAATTGGCAGCCGGCATATTGGTATCGGAGCGCAGCACAAG--TCGCGCTTC-TTTCCCATGAAATGTT-GGCGTCCATCCAA-------------------------------------------------GAAC----</seq>
      </row>
      <row id="Row4268477" otu="Tl3535858">
        <seq>-----------------------------------AGCGGG-TGGGGAAC-CACAGGAACAT----GGGCTCC-----GGCTCGTGCTCCT-GCCCCGTCTTGCTGAAT-ATTCACCCATGTCTTTT-GCGTACTATTTGTTTCCTTGGTGGGCTTGCCCACCGATAGGACAATATC--AAACCTTTT---GTAATTGCAATCAGCGTCAGAAAAA-CTTTAATAGTTACAACTTTCAACAACGGATCTCTTGGTTCTGGCATCGATGAAGAACGCAGCGAAATGCGATAAGTAGTGTGAATTGCAGAATTCAGTGAATCATCGAATCTTTGAACGCACATTGCGCCCCTTGGTATTCCATGGGGCATGCCTGTTCGAGCGTCATTT-GTACCCTCAAGCTTTGCTTGGTGTTGGGCGTC-TTGTCCTC--TTCT----GGAGGACTCGCCTTAAAACAA-TTGGCAGCCGGCATATTGGTATCGGAGCGCAGCACAAG--TCGCACTTC-TTTCC-ATGAA-TGTT-GGCATCCATCAAGACCA--TTTTTTC--ACTCTTGACCTCGGATCAGGTAGGGATACCCGCTGAACTTAA</seq>
      </row>
      <row id="Row4268478" otu="Tl3535851">
        <seq>-----------------------------------AGCGGG-TGGGGAAC-CACAGGAACAT----GGGCTCC-----GGCTCGTGCTCCT-GCCCCGTCTTGCTGAAT-ATTCACCCATGTCTTTT-GCGTACTATTTGTTTCCTTGGTGGGCTTGCCCACCGATAGGACAATATC--AAACCTTTT---GTAATTGCAATCAGCGTCAGAAAAA-CTTTAATAGTTACAACTTTCAACAACGGATCTCTTGGTTCTGGCATCGATGAAGAACGCAGCGAAATGCGATAAGTAGTGTGAATTGCAGAATTCAGTGAATCATCGAATCTTTGAACGCACATTGCGCCCCTTGGTATTCCATGGGGCATGCCTGTTCGAGCGTCATTT-GTACCCTCAAGCTTTGCTTGGTGTTGGGCGTC-TTGTCCTC--TTCT----GGAGGACTCGCCTTAAAACAA-TTGGCAGCCGGCATATTGGTATCGGAGCGCAGCACAAG--TCGCACTTC-TTTCC-ATGAA-TGTT-GGCATCCATCAAGACCA--TTTTTTC--ACTCTTGACCTCGGATCAGGTAGGGATACCCGCTGAACTTAA</seq>
      </row>
      <row id="Row4268479" otu="Tl3535861">
        <seq>----------------------------------AAGCGGG-TGGGGAAC-CACAGGAACAT----GGGCTCC-----GGCTCGTGCTCCT-GCCCCGTCTTGCTGAAT-ATTCACCCATGTCTTTT-GCGTACTATTTGTTTCCTTGGTGGGCTTGCCCACCGATAGGACAATATC--AAACCTTTT---GTAATTGCAATCAGCGTCAGAAAAA-CTTTAATAGTTACAACTTTCAACAACGGATCTCTTGGTTCTGGCATCGATGAAGAACGCAGCGAAATGCGATAAGTAGTGTGAATTGCAGAATTCAGTGAATCATCGAATCTTTGAACGCACATTGCGCCCCTTGGTATTCCATGGGGCATGCCTGTTCGAGCGTCATTT-GTACCCTCAAGCTTTGCTTGGTGTTGGGCGTC-TTGTCCTC--TTCT----GGAGGACTCGCCTTAAAACAA-TTGGCAGCCGGCATATTGGTATCGGAGCGCAGCACAAG--TCGCACTTC-TTTCC-ATGAA-TGTT-GGCATCCATCAAGACCA--TTTTTTC--ACTCTTGACCTCGGATCAGGTAGGGATACCCGCTGAACTTAA</seq>
      </row>
      <row id="Row4268480" otu="Tl3535866">
        <seq>------------------------------------------GGGGGAAC-CACAGGAACA-----GGGCTCT-----GGCTCGCGTTTCT-GCCTCATCTTGCTGAAT-ATTCACCCATGTCTTTT-GCGTACTATTTGTTTCCTTGGTGGGCTTGCCCGCCGATAGGACAATATC--AAACCTTTT---GTAATTGCAATCAGCGTCAGAAAAA-CTTTAATAGTTACAACTTTCAACAACGGATCTCTTGGTTCTGGCATCGATGAAGAACGCAGCGAAATGCGATAAGTAGTGTGAATTGCAGAATTCAGTGAATCATCGAATCTTTGAACGCACATTGCGCCCCTTGGTATTCCATGGGGCATGCCTGTTCGAGCGTCATTT-GTACCCTCAAGCTCTGCTTGGTGTTGGGCGTC-TTGTCCCCCTTTTT----GGAGGACTCGCCTTAAAACAA-TTGGCAGCCGGCATATTGGTATCGGAGCGCAGCACAAG--TCGCACTTC-TTTCC-ATGAA-TGTTTGGCATCCATCAAGACCA--TTTTTTC--ACTCTTGACCTCGGATCAGGTAGGGATACCCGCTGAACTTAA</seq>
      </row>
      <row id="Row4268481" otu="Tl3535872">
        <seq>---------GCGAGAG-ATCATTAC-CAATATGAAAGCGGG-TGGGGAAC-CACAGGAACAA----GGGCTCT-----GGCTCGCGTTTCT-GCCTCATCTTGCTGAAT-ATTCACCCATGTCTTTT-GCGTACTATTTGTTTCCTTGGTGGGCTTGCCCGCCGATAGGACAATATC--AAACCTTTT---GTAATTGCAATCAGCGTCAGAAAAA-CTTTAATAGTTACAACTTTCAACAACGGATCTCTTGGTTCTGGCATCGATGAAGAACGCAGCGAAATGCGATAAGTAGTGTGAATTGCAGAATTCAGTGAATCATCGAATCTTTGAACGCACATTGCGCCCCTTGGTATTCCATGGGGCATGCCTGTTCGAGCGTCATTT-GTACCCTCAAGCTCTGCTTGGTGTTGGGCGTC-TTGTCCCCCTTTTT----GGAGGACTCGCCTTAAAACAA-TTGGCAGCCGGCATATTGGTATCGGAGCGCAGCACAAG--TCGCACTTC-TTTCC-ATGAA-TGTTTGGCATCCATCAAGACCA--TTTTTTC--ACTCTTGACCTCGGATCAGGTAGGGATACCCGCTGAACTTAA</seq>
      </row>
      <row id="Row4268482" otu="Tl3535868">
        <seq>----------------------------------AAGCGGG-TGGGGAAC-CACAGGAACAA----GGGCTCT-----GGCTCGCGTTTCT-GCCTCATCTTGCTGAAT-ATTCACCCATGTCTTTT-GCGTACTATTTGTTTCCTTGGTGGGCTTGCCCGCCGATAGGACAATATC--AAACCTTTT---GTAATTGCAATCAGCGTCAGAAAAA-CTTTAATAGTTACAACTTTCAACAACGGATCTCTTGGTTCTGGCATCGATGAAGAACGCAGCGAAATGCGATAAGTAGTGTGAATTGCAGAATTCAGTGAATCATCGAATCTTTGAACGCACATTGCGCCCCTTGGTATTCCATGGGGCATGCCTGTTCGAGCGTCATTT-GTACCCTCAAGCTCTGCTTGGTGTTGGGCGTC-TTGTCCCCCTTTTT----GGAGGACTCGCCTTAAAACAA-TTGGCAGCCGGCATATTGGTATCGGAGCGCAGCACAAG--TCGCACTTC-TTTCC-ATGAA-TGTTTGGCATCCATCAAGACCA--TTTTTTC--ACTCTTGACCTCGGATCAGGTAGGGATACCCGCTGAACTTAA</seq>
      </row>
      <row id="Row4268483" otu="Tl3535864">
        <seq>----------------------------------AAGCGGG-TGGGGAAC-CACAGGAACA-----GGGCTCT-----GGCTCGCGTTTCT-GCCTCATCTTGCTGAAT-ATTCACCCATGTCTTTT-GCGTACTATTTGTTTCCTTGGTGGGCTTGCCCGCCGATAGGACAATATC--AAACCTTTT---GTAATTGCAATCAGCGTCAGAAAAA-CTTTAATAGTTACAACTTTCAACAACGGATCTCTTGGTTCTGGCATCGATGAAGAACGCAGCGAAATGCGATAAGTAGTGTGAATTGCAGAATTCAGTGAATCATCGAATCTTTGAACGCACATTGCGCCCCTTGGTATTCCATGGGGCATGCCTGTTCGAGCGTCATTT-GTACCCTCAAGCTCTGCTTGGTGTTGGGCGTC-TTGTCCCCCTTTTT----GGAGGACTCGCCTTAAAACAA-TTGGCAGCCGGCATATTGGTATCGGAGCGCAGCACAAG--TCGCACTTC-TTTCC-ATGAA-TGTTTGGCATCCATCAAGACCA--TTTTTTC--ACTCTTGACCTCGGATCAGGTAGGGATACCCGCTGAACTTAA</seq>
      </row>
      <row id="Row4268484" otu="Tl3626491">
        <seq>------------------------------ATG-AAGCGGG-TGGGGGAC-CACGGGAACAT----GGGCTTC-----GGCTCGCGTTTCT-GCCCCGTCTTGCTGAAT-ATCCTCCCATGTCTTTT-GCGTACTATTTGTTTCCTTGGTGGGCTTGCCCACCGATAGGACAATATC--AAACCTTTT---GTAATTGCAATCAGCGTCAGAAAAA-CTTTAATAGTTACAACTTTCAACAACGGATCTCTTGGTTCTGGCATCGATGAAGAACGCAGCGAAATGCGATAAGTAGTGTGAATTGCAGAATTCAGTGAATCATCGAATCTTTGAACGCACATTGCGCCCCTTGGTATTCCATGGGGCATGCCTGTTCGAGCGTCATTT-GTACCCTCAAGCTTTGCTTGGTGTTGGGCGTC-TTGTCCTC--TTCT----GGAGGAGTCCCCTCAAAACAA-TTGGCAGCCGGCATATTGGTATCGGAGCGCAGCACAAG--TCGCACTTT-GTTCC-ATGAA-TGTT-GGCATCCATCAAGACCA--TTTTTTC--ACTCTTGACCTCG-----------------------------</seq>
      </row>
      <row id="Row4268485" otu="Tl3626486">
        <seq>------------------------------TTGTAGGCGGG-TGGGG-AC-CACGGGA-CAT----GGGCTTC-----GGCTCGCGTTTCT-GCCCCGTCTTGCTGAAT-ATTCACCCATGTCTTTT-GCGTACTATTTGTTTCCTTGGTGGGCTTGCCCACCGATAGGACAATATC--AAACCTTTT---GTAATTGCAATCAGCGTCAGAAAAA-CTTTAATAGTTACAACTTTCAACAACGGATCTCTTGGTTCTGGCATCGATGAAGAACGCAGCGAAATGCGATAAGTAGTGTGAATTGCAGAATTCAGTGAATCATCGAATCTTTGAACGCACATTGCGCCCCTTGGTATTCCATGGGGCATGCCTGTTCGAGCGTCATTT-GTACCCTCAAGCTTTGCTTGGTGTTGGGCGTC-TTGTCCTC--TTCT----GGAGGACTCGCCTCAAAACAA-TTGGCAGCCGGCATATTGGTATCGGAGCGCAGCACAAG--TCGCACTTT-GTTCC-ATGAA-TGTT-GGCATCCATCAAGACCA--TTTTTTC--ACTCTTGACCTCGGATCAGGTAGGGATACCCGC---------</seq>
      </row>
      <row id="Row4268486" otu="Tl3535847">
        <seq>-----ACAAGCGGAAGGATCATTAC-CAATATGAAAGCGGA-TGGGGAAC-CACGGACACGT----GGGCTTC-----GGCTCTCGTTTCT-GCCCCATCTTGCTGAAT-ATTCACCCATGTCTTTT-GCGTACTATTTGTTTCCTTGGTGGGCTTGCCCACCGATAGGACAATATC--AAACCTTTT---GCAATTGCAATCAGCGTCAGAAAAA-CTTTAATAGTTACAACTTTCAACAACGGATCTCTTGGTTCTGGCATCGATGAAGAACGCAGCGAAATGCGATAAGTAGTGTGAATTGCAGAATTCAGTGAATCATCGAATCTTTGAACGCACATTGCGCCCCTTGGTATTCCATGGGGCATGCCTGTTCGAGCGTCATTT-GTACCCTCAAGCTTTGCTTGGTGTTGGGCGTC-TTGTCCTC--TTCT----GGAGGACTCGCCTTAAAACAA-TTGGCAGCCGGCATATTGGTATCGGAGCGCAGCACAAG--TCGCACTTC-GTTCC-ATGAA-TGTT-GGCATCCATCAAGACCA--TTTTTTC--ACTCTTGACCTCGGATCAGGTAGGGATACCCGCTGAACTTAA</seq>
      </row>
      <row id="Row4268487" otu="Tl3626492">
        <seq>---------GCGGAAGGATCATTAC---ATAT-TGAGCGTGGCTGGGATC-CCCAAGTGCTGCTGCTTGCCTCTGGTAAGC--GCGATACTTGCCCAGTCTGCGTGAAT-ATTCACCCATGTCTTT--GCGTACTTCTTGTTTCCTTGGTGGGCTTGCCCGCCATTAGGACAAACAT--CAACCTTTT---GTAATTGCAGTCAGCGTCAGTAAAA--TTTAATTATTACAACTTTCAACAACGGATCTCTTGGTTCTGGCATCGATGAAGAACGCAGCGAAATGCGATAAGTAGTGTGAATTGCAGAATTCAGTGAATCATCGAATCTTTGAACGCACATTGCGCCCATTGGTATTCCAATGGGCATGCCTGTTCGAGCGTCATTT-GTACCCTCAAGCCTTGCTTGGTGTTGGGCGT--TTGTC--CTTT---------GGGACTCGCCTTAAAAGGA-TTGGCAGCCGGCATATTGGT-TCGGAGCGCAGCACAAA--TTGCGGTCT-C-TCC-ATGAA-TGTC-GGCGTCCATGAAGCCC---ATTTTTC--ACTTTTGACCTCGGATCAGGTAGGGATACCCGCTGAACTTAA</seq>
      </row>
      <row id="Row4268488" otu="Tl3626484">
        <seq>---------GCGGAAGGATCATTAC-CAATAT-AAAGCG-GGCTGGGACC-CCCAGAAGCG------TGCTCC-----GGC--GTGCTGCT-GCCCGGCCTTGCTGAAT-ATTCACCCATGTCTTTT-GCGTACTACTTGTTTCCTCGGTGGGCCTGCCCACCAGCAGGACATAATT--AAACCTTTT---GTAATTGCAATCAGCGTCAGAAAAA--CATAATTGTTACAACTTTCAACAACGGATCTCTTGGTTCTGGCATCGATGAAGAACGCAGCGAAATGCGATAAGTAGTGTGAATTGCAGAATTCAGTGAATCATCGAATCTTTGAACGCACATTGCGCCCTTTGGTATTCCAAAGGGCATGCCTGTTCGAGCGTCATTT-GAACCCTCAAGCCTTGCTTGGTGTTGGGCGT--TTGTCTCCTTG---------GGGACTCGCCTCAAAATAA-TTGGCAGCCGGCACATTGGTATTGAAGCGCAGCACATT--TTGCGCTCC-TGTCC-ATGCG-TGTC-CGCGTCCACGAAGCTC---TATTTTC--ACTTTTGACCTCGGATCAGGTAGGGATACCCGCTGAACTTAA</seq>
      </row>
      <row id="Row4268489" otu="Tl3626490">
        <seq>----AACAAGCGGAGGGATCATTACACAATATGAAAGCGGG-TTGGGACCTCAT----------------CTC---------GGTGGGGGC--TCCAGCTTGTCTGAATTATTCACCCATGTCTTTT-GCGCACTTCTTGTTTCCTGGGCGGGTTCGCCCGCCACCAGGACCCAACCATAAACCTTTTTTTGTAATTGCAATCAGCGTCAGTAAACAATGTAATTATTACAACTTTCAACAACGGATCTCTTGGTTCTGGCATCGATGAAGAACGCAGCGAAATGCGATACGTAGTGTGAATTGCAGAATTCAGTGAATCATCGAATCTTTGAACGCACATTGCGCCCTTTGGTATTCCAAAGGGCATGCCTGTTCGAGCGTCATTT-GTACCCTCAAGCTTTGCTTGGTGTTGGGCGTCTTTGTCTCTCAC---------GAGACTCGCCTTAAAATGA-TTGGCAGCCGGCCTACTGGTTTCGGAGCGCAGCACAAT-CTTGCACTTCTGATCAGCCATG--GTTGAGCATCCATCAAGACCACATTTTTCTCA-CTTTTGACCTCGGATCAGGTAGGGATACCCGCTGAACTTAA</seq>
      </row>
      <row id="Row4268490" otu="Tl3626485">
        <seq>-----------------ATCATTACACAATATGAAAGCGGG-TTGGGACCTCAC----------------CTC---------GGTGAGGGC--TCCAGCTTGTCTGAATTATTCACCCATGTCTTTT-GCGCACTTCTTGTTTCCTGGGCGGGTTCGCCCGCCACCAGGACCAAACCATAAACCTTTTT--GTAATTGCAATCAGCGTCAGTAAACAATGTAATTATTACAACTTTCAACAACGGATCTCTTGGTTCTGGCATCGATGAAGAACGCAGCGAAATGCGATACGTAGTGTGAATTGCAGAATTCAGTGAATCATCGAATCTTTGAACGCACATTGCGCCCTTTGGTATTCCAAAGGGCATGCCTGTTCGAGCGTCATTT-GTACCCTCAAGCTTTGCTTGGTGTTGGGCGTCTTTGTCTCTCAC---------GAGACTCGCCTTAAAATGA-TTGGCAGCCGACCTACTGGTTTCGGAGCGCAGCACAATTCTTGCACTTTGAATCAGCCTTG--GTTGAGCATCCATCAAGACCACATTTTTTTCAACTTTTGACCTC------------------------------</seq>
      </row>
      <row id="Row4268491" otu="Tl3626489">
        <seq>GCGTAACAAGCGGAGGGATCATTACACAATAACAAGGCGGG-CTGG---CTCTC----------------TCC---------CGGGAGGAC--T--GGCCTTGCTGAATTATTCACCCGTGTCTTTT-GCGTACTTCTTGTTTCCTGGGCGGGTTCGCCCGCCACCAGGACCC--CCATAAACCTTTT---GCAATGGCAATCAGCGTCAGTAA-CAACACAATAATTACAACTTTCAACAACGGATCTCTTGGTTCTGGCATCGATGAAGAACGCAGCGAAATGCGATAAGTAGTGTGAATTGCAGAATTCAGTGAATCATCGAATCTTTGAACGCACATTGCGCCCTTTGGTATTCCAAAGGGCATGCCTGTTCGAGCGTCATTT-GTACCCTCAAGCTTTGCTTGGTGTTGGGCGTCTTTGTCTCCGGCTTGCCT--GGAGACTCGCCTTAAAGTGA-TTGGCAGCCGGCCTACTGGTTTCGGAGCGCAGCACAAG--TCGCGCTCTCTTCCAGCCAAG--GTC-AGCGTCCACCAAG-CCACCTTTTTT---ACCTTTGACCTCGGATCAGGTAGGGATACCCGCTGAACTTAA</seq>
      </row>
    </matrix>
  </characters>
  <trees about="#Tb49441" id="Tb49441" label="Neocamarosporium" otus="Tls68705" xml:base="http://purl.org/phylo/treebase/phylows/tree/TB2:">
    <meta content="Mapped from TreeBASE schema using org.cipres.treebase.domain.nexus.nexml.NexmlTreeBlockWriter@33c113a4 $Rev$" datatype="xsd:string" id="meta3196164" property="skos:historyNote" xsi:type="nex:LiteralMeta"/>
    <meta href="S24085" id="meta3196163" rel="rdfs:isDefinedBy" xsi:type="nex:ResourceMeta"/>
    <tree about="#Tr117318" id="Tr117318" label="Imported tree 1" xsi:type="nex:FloatTree">
      <meta content="39" datatype="xsd:integer" id="meta3196170" property="tb:ntax.tree" xsi:type="nex:LiteralMeta"/>
      <meta content="Unrated" datatype="xsd:string" id="meta3196169" property="tb:quality.tree" xsi:type="nex:LiteralMeta"/>
      <meta content="Single" datatype="xsd:string" id="meta3196168" property="tb:type.tree" xsi:type="nex:LiteralMeta"/>
      <meta content="Species Tree" datatype="xsd:string" id="meta3196167" property="tb:kind.tree" xsi:type="nex:LiteralMeta"/>
      <meta href="http://purl.org/phylo/treebase/phylows/study/TB2:S24085" id="meta3196166" rel="rdfs:isDefinedBy" xsi:type="nex:ResourceMeta"/>
      <node id="Tn18370943"/>
      <node id="Tn18370997"/>
      <node id="Tn18370993"/>
      <node id="Tn18370967"/>
      <node id="Tn18370963"/>
      <node id="Tn18370946"/>
      <node id="Tn18370994"/>
      <node id="Tn18370988"/>
      <node id="Tn18370990"/>
      <node id="Tn18370955"/>
      <node id="Tn18371003"/>
      <node id="Tn18370987"/>
      <node id="Tn18370936" label="Neocamarosporium betae CBS 109410" otu="Tl3535853"/>
      <node id="Tn18370970" label="Neocamarosporium betae CBS 112 85" otu="Tl3535852"/>
      <node id="Tn18370954" label="Neocamarosporium betae CBS 523 66" otu="Tl3535871"/>
      <node id="Tn18370968" label="Neocamarosporium betae CBS 236 28" otu="Tl3535865"/>
      <node id="Tn18370937" label="Neocamarosporium betae CBS 111 85" otu="Tl3535870"/>
      <node id="Tn18370940" label="Neocamarosporium solicola IBRC M 30257 TYPE" otu="Tl3626487"/>
      <node id="Tn18370983"/>
      <node id="Tn18370953" label="Neocamarosporium phragmitis MFLUCC 17 0756 TYPE" otu="Tl3535863"/>
      <node id="Tn18370944"/>
      <node id="Tn18370974"/>
      <node id="Tn18370952" label="Neocamarosporium calvescens CBS 246 79" otu="Tl3535874"/>
      <node id="Tn18370939" label="Neocamarosporium calvescens CBS 343 78" otu="Tl3535860"/>
      <node id="Tn18370948"/>
      <node id="Tn18371001" label="Neocamarosporium calvescens CBS 215 57" otu="Tl3535848"/>
      <node id="Tn18371004"/>
      <node id="Tn18370958" label="Neocamarosporium obiones CBS 432 77" otu="Tl3535869"/>
      <node id="Tn18370945" label="Neocamarosporium obiones CBS 786 68" otu="Tl3535849"/>
      <node id="Tn18370950"/>
      <node id="Tn18370998" label="Neocamarosporium lamiacearum MFLU 15 2989 TYPE" otu="Tl3535875"/>
      <node id="Tn18370982" label="Neocamarosporium lamiacearum MFLUCC 17 0750" otu="Tl3535859"/>
      <node id="Tn18370956" label="Neocamarosporium korfii MFLUCC 17 0745 TYPE" otu="Tl3535855"/>
      <node id="Tn18370951"/>
      <node id="Tn18371008" label="Neocamarosporium goegapense CBS 138008 TYPE" otu="Tl3626494"/>
      <node id="Tn18371006" label="Neocamarosporium salsolae MFLU 17 0192 TYPE" otu="Tl3535850"/>
      <node id="Tn18370938"/>
      <node id="Tn18370972" label="Neocamarosporium salicorniicola MFLU 15 0957 TYPE" otu="Tl3535877"/>
      <node id="Tn18370971"/>
      <node id="Tn18370961"/>
      <node id="Tn18370973"/>
      <node id="Tn18370942" label="Neocamarosporium aestuarinum CAA 803" otu="Tl3535876"/>
      <node id="Tn18370964" label="Neocamarosporium aestuarinum MUM 18 55 CMG 4 TYPE" otu="Tl3535846"/>
      <node id="Tn18370986" label="Neocamarosporium jorjanensis IBRC M 30243 TYPE" otu="Tl3626493"/>
      <node id="Tn18370999"/>
      <node id="Tn18370991"/>
      <node id="Tn18370969"/>
      <node id="Tn18370978" label="Neocamarosporium chichastianum CBS 137502 TYPE" otu="Tl3626491"/>
      <node id="Tn18371010" label="Neocamarosporium persepolisi IBRC M 30134 TYPE" otu="Tl3626486"/>
      <node id="Tn18370949" label="Neocamarosporium chersinae CPC 27298 TYPE" otu="Tl3535847"/>
      <node id="Tn18370959"/>
      <node id="Tn18371000"/>
      <node id="Tn18370985"/>
      <node id="Tn18371007" label="Neocamarosporium halimiones CAA 806" otu="Tl3535861"/>
      <node id="Tn18371002" label="Neocamarosporium halimiones MUM 18 54 CAA 807 TYPE" otu="Tl3535858"/>
      <node id="Tn18370981" label="Neocamarosporium halimiones CAA 805" otu="Tl3535851"/>
      <node id="Tn18370977"/>
      <node id="Tn18370979" label="Neocamarosporium endophyticum CAA 804" otu="Tl3535864"/>
      <node id="Tn18371009"/>
      <node id="Tn18370980" label="Neocamarosporium endophyticum CAA 809" otu="Tl3535866"/>
      <node id="Tn18370935"/>
      <node id="Tn18370976" label="Neocamarosporium endophyticum CMG 10" otu="Tl3535872"/>
      <node id="Tn18370975" label="Neocamarosporium endophyticum MUM 18 56 CAA 808 TYPE" otu="Tl3535868"/>
      <node id="Tn18370941"/>
      <node id="Tn18370984"/>
      <node id="Tn18370992" label="Comoclathris spartii MFLUCC 13 0214 TYPE" otu="Tl3626492"/>
      <node id="Tn18370996"/>
      <node id="Tn18370966" label="CBS 193 86 TYPE" otu="Tl3626489"/>
      <node id="Tn18370960"/>
      <node id="Tn18370962" label="Paradendryphiella salina CBS 142 60 TYPE" otu="Tl3626490"/>
      <node id="Tn18370947" label="Stemphylium vesicarium CBS 191 86 TYPE" otu="Tl3626485"/>
      <node id="Tn18370965" label="Libertasomyces quercus CBS 134 97 TYPE" otu="Tl3626484"/>
      <node id="Tn18370989"/>
      <node id="Tn18371005" label="Foliophoma fallens CBS 161 78" otu="Tl3626495"/>
      <node id="Tn18370995" label="Foliophoma fallens CBS 284 70" otu="Tl3626488"/>
      <node id="Tn18370957" label="Pyrenochaetopsis tabarestanensis IBRC M 30051 TYPE" otu="Tl3535873"/>
      <edge id="edge3196173" length="0.05840711" source="Tn18370943" target="Tn18370997"/>
      <edge id="edge3196175" length="0.03197423" source="Tn18370997" target="Tn18370993"/>
      <edge id="edge3196177" length="0.01789055" source="Tn18370993" target="Tn18370967"/>
      <edge id="edge3196179" length="0.00367404" source="Tn18370967" target="Tn18370963"/>
      <edge id="edge3196181" length="0.02732418" source="Tn18370963" target="Tn18370946"/>
      <edge id="edge3196183" length="0.03543053" source="Tn18370946" target="Tn18370994"/>
      <edge id="edge3196185" length="0.02682554" source="Tn18370994" target="Tn18370988"/>
      <edge id="edge3196187" length="0.02157614" source="Tn18370988" target="Tn18370990"/>
      <edge id="edge3196189" length="0.00412815" source="Tn18370990" target="Tn18370955"/>
      <edge id="edge3196191" length="0.0" source="Tn18370955" target="Tn18371003"/>
      <edge id="edge3196193" length="0.0" source="Tn18371003" target="Tn18370987"/>
      <edge id="edge3196195" length="0.0" source="Tn18370987" target="Tn18370936"/>
      <edge id="edge3196197" length="0.0" source="Tn18370987" target="Tn18370970"/>
      <edge id="edge3196199" length="0.0" source="Tn18371003" target="Tn18370954"/>
      <edge id="edge3196201" length="0.0" source="Tn18370955" target="Tn18370968"/>
      <edge id="edge3196203" length="0.0" source="Tn18370990" target="Tn18370937"/>
      <edge id="edge3196205" length="0.02444558" source="Tn18370988" target="Tn18370940"/>
      <edge id="edge3196207" length="0.01775516" source="Tn18370994" target="Tn18370983"/>
      <edge id="edge3196209" length="0.00203984" source="Tn18370983" target="Tn18370953"/>
      <edge id="edge3196211" length="0.00265091" source="Tn18370983" target="Tn18370944"/>
      <edge id="edge3196213" length="0.0" source="Tn18370944" target="Tn18370974"/>
      <edge id="edge3196215" length="0.00203967" source="Tn18370974" target="Tn18370952"/>
      <edge id="edge3196217" length="0.00253092" source="Tn18370974" target="Tn18370939"/>
      <edge id="edge3196219" length="0.0" source="Tn18370944" target="Tn18370948"/>
      <edge id="edge3196221" length="0.00204836" source="Tn18370948" target="Tn18371001"/>
      <edge id="edge3196223" length="0.00430621" source="Tn18370948" target="Tn18371004"/>
      <edge id="edge3196225" length="0.0" source="Tn18371004" target="Tn18370958"/>
      <edge id="edge3196227" length="0.0" source="Tn18371004" target="Tn18370945"/>
      <edge id="edge3196229" length="0.04342095" source="Tn18370946" target="Tn18370950"/>
      <edge id="edge3196231" length="0.0" source="Tn18370950" target="Tn18370998"/>
      <edge id="edge3196233" length="0.00167224" source="Tn18370950" target="Tn18370982"/>
      <edge id="edge3196235" length="0.01141934" source="Tn18370963" target="Tn18370956"/>
      <edge id="edge3196237" length="0.00829928" source="Tn18370967" target="Tn18370951"/>
      <edge id="edge3196239" length="0.0020204" source="Tn18370951" target="Tn18371008"/>
      <edge id="edge3196241" length="0.00167224" source="Tn18370951" target="Tn18371006"/>
      <edge id="edge3196243" length="0.02659747" source="Tn18370993" target="Tn18370938"/>
      <edge id="edge3196245" length="0.02700399" source="Tn18370938" target="Tn18370972"/>
      <edge id="edge3196247" length="0.0" source="Tn18370938" target="Tn18370971"/>
      <edge id="edge3196249" length="0.01764359" source="Tn18370971" target="Tn18370961"/>
      <edge id="edge3196251" length="0.01564788" source="Tn18370961" target="Tn18370973"/>
      <edge id="edge3196253" length="0.0" source="Tn18370973" target="Tn18370942"/>
      <edge id="edge3196255" length="0.00192943" source="Tn18370973" target="Tn18370964"/>
      <edge id="edge3196257" length="0.01145335" source="Tn18370961" target="Tn18370986"/>
      <edge id="edge3196259" length="0.00574658" source="Tn18370971" target="Tn18370999"/>
      <edge id="edge3196261" length="0.00252145" source="Tn18370999" target="Tn18370991"/>
      <edge id="edge3196263" length="0.00854757" source="Tn18370991" target="Tn18370969"/>
      <edge id="edge3196265" length="0.00999641" source="Tn18370969" target="Tn18370978"/>
      <edge id="edge3196267" length="0.00501279" source="Tn18370969" target="Tn18371010"/>
      <edge id="edge3196269" length="0.0123231" source="Tn18370991" target="Tn18370949"/>
      <edge id="edge3196271" length="0.00435962" source="Tn18370999" target="Tn18370959"/>
      <edge id="edge3196273" length="0.00827752" source="Tn18370959" target="Tn18371000"/>
      <edge id="edge3196275" length="0.0" source="Tn18371000" target="Tn18370985"/>
      <edge id="edge3196277" length="0.0" source="Tn18370985" target="Tn18371007"/>
      <edge id="edge3196279" length="0.0" source="Tn18370985" target="Tn18371002"/>
      <edge id="edge3196281" length="0.0" source="Tn18371000" target="Tn18370981"/>
      <edge id="edge3196283" length="0.01869568" source="Tn18370959" target="Tn18370977"/>
      <edge id="edge3196285" length="0.0" source="Tn18370977" target="Tn18370979"/>
      <edge id="edge3196287" length="0.0" source="Tn18370977" target="Tn18371009"/>
      <edge id="edge3196289" length="0.00205684" source="Tn18371009" target="Tn18370980"/>
      <edge id="edge3196291" length="0.0" source="Tn18371009" target="Tn18370935"/>
      <edge id="edge3196293" length="0.0" source="Tn18370935" target="Tn18370976"/>
      <edge id="edge3196295" length="0.0" source="Tn18370935" target="Tn18370975"/>
      <edge id="edge3196297" length="0.06202805" source="Tn18370997" target="Tn18370941"/>
      <edge id="edge3196299" length="0.02277576" source="Tn18370941" target="Tn18370984"/>
      <edge id="edge3196301" length="0.08494887" source="Tn18370984" target="Tn18370992"/>
      <edge id="edge3196303" length="0.11830614" source="Tn18370984" target="Tn18370996"/>
      <edge id="edge3196305" length="0.07443681" source="Tn18370996" target="Tn18370966"/>
      <edge id="edge3196307" length="0.04228824" source="Tn18370996" target="Tn18370960"/>
      <edge id="edge3196309" length="0.00955399" source="Tn18370960" target="Tn18370962"/>
      <edge id="edge3196311" length="0.01076595" source="Tn18370960" target="Tn18370947"/>
      <edge id="edge3196313" length="0.06727268" source="Tn18370941" target="Tn18370965"/>
      <edge id="edge3196315" length="0.06095941" source="Tn18370943" target="Tn18370989"/>
      <edge id="edge3196317" length="0.0027092" source="Tn18370989" target="Tn18371005"/>
      <edge id="edge3196319" length="0.00355619" source="Tn18370989" target="Tn18370995"/>
      <edge id="edge3196321" length="0.21061446" source="Tn18370943" target="Tn18370957"/>
    </tree>
  </trees>
</nex:nexml>
